Workbook

Sheet Study Guide
A1: ETERNAL LTD. — STUDY GUIDE
A2: Purpose | B2: This is an undergraduate investment-research project. The aim is to understand how Eternal could create value across food delivery, quick commerce, going-out and B2B supplies.
A3: Main question | B3: Does the multi-business ecosystem create economic value, or is it just a collection of different businesses?
A5: THE MODEL IN ONE LINE | B5: Historical numbers → operating assumptions → forecast → DCF/SOTP → investment conclusion
A7: STEP 1 — Understand the businesses | B7: Zomato = food delivery; Blinkit = quick commerce; District = going-out; Hyperpure = B2B supplies.
A8: STEP 2 — Look at history | B8: Start with FY23–FY26 and ask: Is revenue growing? Are margins improving? Which business is driving growth?
A9: STEP 3 — Forecast the businesses | B9: For each major business, estimate growth and an eventual EBITDA margin. These are my assumptions, not company guidance.
A10: STEP 4 — Build group EBITDA | B10: Revenue × EBITDA margin gives a simple operating-profit view. Then combine the businesses.
A11: STEP 5 — Value the company | B11: DCF asks: What are future cash flows worth today? SOTP asks: What if each business is valued separately?
A12: STEP 6 — Compare with market price | B12: Compare my estimated value per share with the current share price. Then decide what the market seems to be assuming.
A14: NUMBERS I MUST KNOW | B14: Current share price: ₹316.80 | Base DCF: ~₹187/share | Base SOTP: ~₹258/share | Blended: ~₹223/share
A15: CORE INVESTMENT QUESTION | B15: The biggest debate in my model is whether Blinkit can keep growing rapidly while eventually reaching sustainable EBITDA margins.
A17: WORDS TO KNOW | B17: NOV = Net Order Value. EBITDA = operating profit before depreciation, interest and tax. DCF = Discounted Cash Flow. SOTP = Sum-of-the-Parts. WACC = discount rate used for DCF. Terminal value = value of cash flows after the explicit forecast period.
A19: WHAT I SHOULD NOT MEMORISE | B19: Do not memorise every cell. Understand why the number is there, what assumption drives it, and what happens if that assumption changes.

Sheet Cover
A1: ETERNAL LTD.
A2: Undergraduate Investment Research Project
A3: Prepared by : Gayathri Sudhir
A5: October 2026
A7: Eternal: From Food-Delivery Platform to Multi-Product Consumer Ecosystem
A8: Does Eternal's multi-product ecosystem actually create economic value, or is it simply adding businesses under one corporate umbrella?
A10: KEY OUTPUTS (live — active scenario)
A11: Active scenario | B11: =Assumptions!B32 -> Base
A12: Market price used (₹) | B12: =Assumptions!B19 -> 316.8
A13: DCF value per share (₹) | B13: =Valuation!B43 -> 187.46575
A14: SOTP value per share (₹) | B14: =Valuation!G74 -> 258.3627
A15: Blended value per share (₹) | B15: =Valuation!G77 -> 222.91422
A16: Blended upside / (downside) | B16: =B15/B12-1 -> -0.29635662
A17: WACC | B17: =Assumptions!B13 -> 0.133
A18: Terminal growth | B18: =Assumptions!B16 -> 0.05
A19: FY29E Adj. EBITDA (US$ mn) vs management $1bn goal | B19: ='Operating Model'!F113 -> 971.10099
A21: MODEL CHECKS (all should read OK)
A22: Historical P&L ties to reported PBT and PAT | B22: =IF(AND(SUM(Historical!E34:G34)=0,SUM(Historical!D36:G36)=0),"OK","CHECK") -> OK
A23: Quarterly segment Adj. EBITDA sums to company-reported total | B23: =IF(SUMPRODUCT(ABS('Operating Model'!B27:K27))=0,"OK","CHECK") -> OK
A24: FY26 reported EBITDA + SBC = reported segment results | B24: =IF(AND('Operating Model'!B54=0,'Operating Model'!C54=0),"OK","CHECK") -> OK
A25: Forecast base year ties to quarterly tables | B25: =IF(AND('Operating Model'!C119=0,'Operating Model'!C120=0),"OK","CHECK") -> OK
A26: WACC > terminal growth | B26: =IF(Assumptions!B13>Assumptions!B16,"OK","CHECK") -> OK
A27: Sensitivity-1 centre cell equals DCF value per share | B27: =IF(Valuation!B60=0,"OK","CHECK") -> OK
A29: CONTENTS
A30: Assumptions | B30: WACC, market data, scenario selector (Bear/Base/Bull), operating drivers, SOTP multiples. Every judgement is labelled.
A31: Historical | B31: FY21–FY26 income statement from filings with tie-outs to reported PBT/PAT.
A32: Operating Model | B32: Quarterly segment KPIs, EBITDA bridge, 10-year segment forecast (Zomato, Blinkit, District, Hyperpure, Others).
A33: Valuation | B33: DCF, WACC×g sensitivity, SOTP, scenario summary, further sensitivities and investment thesis.
A34: Mini Projects | B34: 1) Customer LTV 2) Advertising economics 3) Zomato vs Swiggy cross-sell 4) Blinkit implied valuation.
A35: Sources | B35: Every source with Primary/Secondary/Assumption tag, plus open items.
A37: COLOUR CODE
A38: Blue = hardcoded input
A39: Black = formula
A40: Green = link to another sheet
A41: Yellow fill = key judgement assumption (not disclosed)
A42: Study order: Study Guide → Historical → Operating Model → Valuation → Mini Projects → Sources
A43: Educational research project. Not investment advice. Figures marked Secondary or Assumption must be verified before relying on them.

Sheet Assumptions
A1: ETERNAL LTD. — ASSUMPTIONS
A2: Blue = hardcoded input | Black = formula | Green = link to other sheet | Yellow fill = key assumption (judgement, not disclosed). ₹ crore unless stated.
A3: Model Date | B3: 46303 | F3: Date the model inputs were refreshed.
A4: Forecast Period | B4: FY27E–FY36E (10 yrs) | F4: Fiscal year ends 31 March. 10-year explicit period because Blinkit/District margins and growth are still ramping; a 5-year DCF would put most value in a terminal year that has not reached steady state.
A6: VALUATION ASSUMPTIONS
A7: Risk-Free Rate | B7: 0.067 | F7: ASSUMPTION from market data: India 10-yr G-sec ~6.7% (Trading Economics, 7-Jul-2026). Refresh before publishing.
A8: Equity Risk Premium | B8: 0.055 | F8: ASSUMPTION: Indian equity risk premium (INR basis, Rf already embeds sovereign spread). Typical practitioner range 5.0–6.5%.
A9: Beta | B9: 1.2 | F9: ASSUMPTION: no regression run. High-volatility consumer-internet stock; TO VERIFY against Bloomberg / NSE 2-yr weekly beta vs Nifty.
A10: Cost of Equity | B10: =B7+B9*B8 -> 0.133 | F10: CAPM: Rf + Beta × ERP.
A11: Pre-Tax Cost of Debt | B11: 0.09 | F11: ASSUMPTION: Eternal has no financial debt (Mar-2026 balance sheet); only lease liabilities. Cost of debt only matters if debt weight > 0.
A12: Tax Rate | B12: 0.2517 | F12: Indian corporate tax rate, new regime (22% + surcharge + cess = 25.17%).
A13: WACC | B13: =(1-B14)*B10+B14*B11*(1-B12) -> 0.133 | F13: WACC. With zero debt weight, WACC = cost of equity.
A14: Target Debt / (Debt + Equity) | B14: 0 | F14: ASSUMPTION: zero. Leases are treated as operating cost (rent is deducted inside Adjusted EBITDA), so lease liabilities are NOT added to debt.
A15: TERMINAL VALUE
A16: Terminal Growth Rate | B16: 0.05 | F16: ASSUMPTION: long-run nominal INR growth for a mature consumer platform; below FY36E segment growth and below India nominal GDP.
A18: MARKET DATA & EQUITY BRIDGE
A19: Current share price (₹) | B19: 316.8 | F19: REPORTED (secondary): ₹316.80 on NSE, 17-Sep-2026, Anand Rathi share-price page. REFRESH to latest close before publishing.
A20: Shares outstanding — listed, incl. ESOP-trust pool (crore) | B20: 966.75 | F20: DERIVED: ₹919 cr paid-up capital at ₹1 face value (Mar-2026 balance sheet) + 47.75 cr shares allotted to Foodie Bay ESOP Trust (FY25 note 5). Vendor market caps imply ~961–965 cr. Using the higher count = conservative (full dilution).
A21: Market capitalisation (₹ crore) | B21: =B19*B20 -> 306266.4 | F21: Calculated.
A22: Cash & treasury investments (₹ crore) | B22: 18288 | F22: REPORTED: company cash balance incl. treasury bonds/government securities, 30-Jun-2026 (Q1 FY27 shareholder letter, via press). Q4 FY26: 17,972.
A23: Financial debt (₹ crore) | B23: 0 | F23: REPORTED: no borrowings on Mar-2026 consolidated balance sheet.
A24: Contingent GST demands on delivery charges (₹ crore) | B24: 447 | F24: REPORTED: orders/SCNs 420+8+13+6 (Note 6, Q4 FY26 results). Management contests; deducted in full as a conservative haircut.
A25: Valuation date (balance-sheet date of cash) | B25: 46203 | F25: Cash is as at 30-Jun-2026, so DCF is struck at that date and only 9 months of FY27E cash flow is counted.
A26: FY27 year-end | B26: 46477
A27: FY27E stub fraction (share of FY27E cash flow still to come) | B27: =(B26-B25)/365 -> 0.75068493 | F27: Calculated.
A28: USD / INR (for cross-checks only) | B28: 94.6 | F28: DERIVED from HSIE report (market cap ₹2,442 bn = US$25,818 mn, Apr-2026). Used only to compare with management USD guidance.
A30: SCENARIO SELECTOR
A31: Active scenario (1 = Bear, 2 = Base, 3 = Bull) | B31: 2 | F31: Change this cell and every sheet re-computes. Scenario tables on the Valuation sheet marked STATIC were produced by running all three settings.
A32: Active scenario name | B32: =CHOOSE(B31,"Bear","Base","Bull") -> Base
A34: OPERATING DRIVERS | B34: Live | C34: Bear | D34: Base | E34: Bull | F34: Basis / source
A35: Food delivery (Zomato)
A36: NOV growth FY27E | B36: =CHOOSE($B$31,C36,D36,E36) -> 0.2 | C36: 0.15 | D36: 0.2 | E36: 0.22 | F36: Q1 FY27 actual +20.1% YoY; management expects 20%+ trend (Q4 FY26 letter, Q7). Bear = competition (Swiggy Toing / Rapido Ownly) slows growth.
A37: NOV growth FY36E (linear fade from FY27E) | B37: =CHOOSE($B$31,C37,D37,E37) -> 0.08 | C37: 0.06 | D37: 0.08 | E37: 0.09 | F37: ASSUMPTION: fade to India nominal consumption growth+. Growth_t = g0 + (gT−g0)×(t−1)/9.
A38: Adj. EBITDA margin target (% of NOV) | B38: =CHOOSE($B$31,C38,D38,E38) -> 0.06 | C38: 0.05 | D38: 0.06 | E38: 0.07 | F38: FY26 actual 5.3%; Q1 FY27 5.6%; management guides 5–6% range (Q4 FY26 letter). Bull assumes ad/platform-fee mix lifts above range.
A39: Years to reach margin target | B39: =CHOOSE($B$31,C39,D39,E39) -> 3 | C39: 3 | D39: 3 | E39: 3 | F39: ASSUMPTION: straight-line from FY26 actual.
A40: Take rate (adjusted revenue % of NOV) | B40: 0.325 | F40: FY26 actual 30.8%, Q4 FY26 32.0%, Q1 FY27 32.8%. Held flat just above Q4 level.
A41: Quick commerce (Blinkit)
A42: NOV growth FY27E | B42: =CHOOSE($B$31,C42,D42,E42) -> 0.7 | C42: 0.55 | D42: 0.7 | E42: 0.8 | F42: Q1 FY27 +86% YoY. Management: NOV CAGR "north of 60%" for 3 yrs, >4x in 3 yrs (Q4 FY26 letter, Q2). Base 70% fade gives ~63% FY26–29 CAGR.
A43: NOV growth FY36E (linear fade) | B43: =CHOOSE($B$31,C43,D43,E43) -> 0.06 | C43: 0.05 | D43: 0.06 | E43: 0.08 | F43: ASSUMPTION.
A44: Adj. EBITDA margin target (% of NOV) | B44: =CHOOSE($B$31,C44,D44,E44) -> 0.05 | C44: 0.035 | D44: 0.05 | E44: 0.06 | F44: FY26 actual −0.6%; Q1 FY27 +0.6%; management steady-state target raised to 6% (Q1 FY27 call, via Business Standard); earlier 5–6%. Base haircuts to 5%.
A45: Years to reach margin target | B45: =CHOOSE($B$31,C45,D45,E45) -> 5 | C45: 6 | D45: 5 | E45: 4 | F45: ASSUMPTION: Bear is slower because competitive intensity persists.
A46: Take rate (adjusted revenue % of NOV) | B46: 0.92 | F46: Q4 FY26 92.0% after shift to inventory-led (1P) model; Q1 FY27 91.4%.
A47: Going-out (District)
A48: NOV growth FY27E | B48: =CHOOSE($B$31,C48,D48,E48) -> 0.4 | C48: 0.3 | D48: 0.4 | E48: 0.5 | F48: FY26 +42%; Q1 FY27 +60%. Guidance: $3bn NOV and $150mn EBITDA by FY30 (~30%+ growth).
A49: NOV growth FY36E (linear fade) | B49: =CHOOSE($B$31,C49,D49,E49) -> 0.07 | C49: 0.05 | D49: 0.07 | E49: 0.08 | F49: ASSUMPTION.
A50: Adj. EBITDA margin target (% of NOV) | B50: =CHOOSE($B$31,C50,D50,E50) -> 0.04 | C50: 0.01 | D50: 0.04 | E50: 0.06 | F50: FY26 actual −3.4%; Q1 FY27 −2.0%. Guidance implies 5% ($150mn on $3bn). Base haircuts to 4%.
A51: Years to reach margin target | B51: =CHOOSE($B$31,C51,D51,E51) -> 5 | C51: 6 | D51: 5 | E51: 4 | F51: ASSUMPTION.
A52: Take rate (adjusted revenue % of NOV) | B52: 0.105 | F52: FY26 actual 10.4%; Q1 FY27 9.9%.
A53: Hyperpure (B2B supplies)
A54: FY27E revenue (₹ crore) | B54: =CHOOSE($B$31,C54,D54,E54) -> 4400 | C54: 4100 | D54: 4400 | E54: 4700 | F54: Revenue base reset: non-restaurant sales moved to Blinkit (1P) from Q2 FY26, so FY26 (5,366) is not comparable. Q4 FY26 978, Q1 FY27 1,034 (+27% LFL) → ~4,100–4,400 run-rate.
A55: Revenue growth FY28E | B55: =CHOOSE($B$31,C55,D55,E55) -> 0.22 | C55: 0.15 | D55: 0.22 | E55: 0.28 | F55: ASSUMPTION: LFL growth 27–37% recently; fades.
A56: Revenue growth FY36E (linear fade) | B56: =CHOOSE($B$31,C56,D56,E56) -> 0.07 | C56: 0.05 | D56: 0.07 | E56: 0.08 | F56: ASSUMPTION.
A57: Adj. EBITDA margin FY27E (% of revenue) | B57: =CHOOSE($B$31,C57,D57,E57) -> 0.005 | C57: 0.003 | D57: 0.005 | E57: 0.008 | F57: Q4 FY26 0.5%; Q1 FY27 0.6%.
A58: Adj. EBITDA margin target (% of revenue) | B58: =CHOOSE($B$31,C58,D58,E58) -> 0.015 | C58: 0.005 | D58: 0.015 | E58: 0.025 | F58: ASSUMPTION: thin-margin distribution business.
A59: Years to reach margin target | B59: =CHOOSE($B$31,C59,D59,E59) -> 5 | C59: 5 | D59: 5 | E59: 5 | F59: ASSUMPTION.
A60: Others (Bistro / Nugget / new initiatives) and corporate drag
A61: Others Adj. EBITDA loss (% of B2C NOV) | B61: =CHOOSE($B$31,C61,D61,E61) -> 0.0025 | C61: 0.0035 | D61: 0.0025 | E61: 0.0015 | F61: FY26 0.22%; Q1 FY27 0.30% (₹94 cr loss on ₹31,119 cr NOV). Management calls Bistro "an experiment, not a big bet".
A62: Others revenue (% of B2C NOV) | B62: 0.003 | F62: Q1 FY27: ₹95 cr / ₹31,119 cr = 0.31%.
A63: Cost & investment drivers (same in all scenarios)
A64: Share-based payment, FY27E (% of B2C NOV) | B64: 0.0085 | F64: FY26 actual 819 / 95,960 = 0.85%. SBC is deducted as a real cost (it is added back in company Adjusted EBITDA).
A65: Share-based payment, FY36E (% of B2C NOV) | B65: 0.005 | F65: ASSUMPTION: operating leverage on ESOP cost.
A66: Capex, FY27E (% of B2C NOV) | B66: 0.018 | F66: FY26 actual 1,751 / 95,960 = 1.8%. Management raised capex per Blinkit store target to ₹2.5 cr from ₹1 cr (Q1 FY27 call).
A67: Capex, FY36E (% of B2C NOV) | B67: 0.012 | F67: ASSUMPTION: store roll-out matures.
A68: D&A excl. ROU (proxy), FY27E (% of B2C NOV) | B68: 0.012 | F68: FY26: D&A 1,597 − lease principal 471 = 1,126 → 1.17% of NOV (proxy; ROU depreciation not separately extracted).
A69: D&A excl. ROU, FY36E (% of B2C NOV) | B69: 0.011 | F69: ASSUMPTION: converges toward capex but stays below while growing.
A70: Working-capital investment (% of incremental B2C NOV) | B70: 0.01 | F70: FY26 actual was 3.6% (see Operating Model calibration) but inflated by 1P transition and seller settlements. ASSUMPTION: 1.0%.
A72: SOTP MULTIPLES (applied to FY28E metrics, valued at Mar-2028, then discounted)
A73: Food delivery: EV / Adj. EBITDA (x) | B73: 35 | F73: ASSUMPTION. Context only (secondary): HSIE Q4 FY26 review uses 45x Mar-28 EBITDA. Haircut because food-delivery growth is ~19% and margin is capped at 5–6% of NOV.
A74: Blinkit: steady-state EV / EBITDA applied to target margin (x) | B74: 25 | F74: ASSUMPTION: EV/NOV = margin target × this multiple (base 5.0% × 25x = 1.25x NOV). Context only: HSIE uses 1.5x Mar-28 NOV.
A75: District: steady-state EV / EBITDA applied to target margin (x) | B75: 20 | F75: ASSUMPTION: EV/NOV = margin target × this multiple (base 4% × 20x = 0.8x NOV). Context only: HSIE uses 1.0x GOV.
A76: Hyperpure: EV / revenue (x) | B76: 0.4 | F76: ASSUMPTION. Context only: HSIE uses 0.5x sales.
A77: Others: capitalisation multiple on EBITDA loss (x) | B77: 10 | F77: ASSUMPTION: negative value = capitalised cost of experiments / corporate drag.

Sheet Historical
A1: ETERNAL LTD. — HISTORICAL INCOME STATEMENT (₹ crore, consolidated)
A2: Blue = hardcoded Reported input | Black = formula (Calculated) | Yellow = still to pull from filings
A3: Fiscal Year | B3: FY21 | C3: FY22 | D3: FY23 | E3: FY24 | F3: FY25 | G3: FY26
A4: Source / Status | B4: Revenue only. SECONDARY (Screener.in consolidated). Verify vs AR FY22 comparative column. | C4: Revenue only. Business Standard / Inc42 report 4,192.4 (matches Screener). Line items TO PULL from AR FY22 (BSE). | D4: Reported — Zomato AR FY24, Consolidated Statement of P&L, comparative column (FY23). Read via Scribd copy of the AR; confirm vs official PDF. | E4: Reported — Zomato AR FY24, Consolidated Statement of P&L (FY24). Delivery charges: AR FY24 MD&A (3,915). Read via Scribd copy of the AR. | F4: Reported — Eternal Q4FY26 results filing (28-Apr-2026), consolidated P&L, comparative column (FY25, audited). | G4: Reported — Eternal Q4FY26 results filing (28-Apr-2026), consolidated P&L (FY26, audited). Deloitte unmodified opinion.
A6: Revenue from operations | B6: 1994 | C6: 4192 | D6: 7079 | E6: 12114 | F6: 20243 | G6: 54364
A7: Other income | D7: 682 | E7: 847 | F7: 1077 | G7: 1396
A8: Total income | D8: =D6+D7 -> 7761 | E8: =E6+E7 -> 12961 | F8: =F6+F7 -> 21320 | G8: =G6+G7 -> 55760
A10: Cost of materials consumed | D10: 0 | E10: 0 | F10: 0 | G10: 54
A11: Purchases of stock-in-trade | D11: 1438 | E11: 2887 | F11: 5653 | G11: 32115
A12: Changes in inventories | D12: -43 | E12: -5 | F12: -88 | G12: -2002
A13: Employee benefit expense | D13: 1465 | E13: 1659 | F13: 2558 | G13: 3536
A14: Other expenses (total; see memo rows 28-30) | D14: 5429 | E14: 7531 | F14: =SUM(F28:F30) -> 11483 | G14: =SUM(G28:G30) -> 19453
A15: Total operating expenses (before D&A, finance cost) | D15: =SUM(D10:D14) -> 8289 | E15: =SUM(E10:E14) -> 12072 | F15: =SUM(F10:F14) -> 19606 | G15: =SUM(G10:G14) -> 53156
A17: EBITDA (excl. other income) | D17: =D6-D15 -> -1210 | E17: =E6-E15 -> 42 | F17: =F6-F15 -> 637 | G17: =G6-G15 -> 1208
A18: Depreciation and amortisation | D18: 437 | E18: 526 | F18: 863 | G18: 1597
A19: Finance costs | D19: 49 | E19: 72 | F19: 154 | G19: 392
A20: Profit before tax | D20: =D8-D15-D18-D19 -> -1014 | E20: =E8-E15-E18-E19 -> 291 | F20: =F8-F15-F18-F19 -> 697 | G20: =G8-G15-G18-G19 -> 615
A21: Tax expense / (credit) | D21: =D20-D35 -> -43 | E21: =E20-E35 -> -60 | F21: =231-61 -> 170 | G21: =319-70 -> 249
A22: Profit after tax | D22: =D20-D21 -> -971 | E22: =E20-E21 -> 351 | F22: =F20-F21 -> 527 | G22: =G20-G21 -> 366
A24: EBITDA margin | D24: =D17/D6 -> -0.1709281 | E24: =E17/E6 -> 0.0034670629 | F24: =F17/F6 -> 0.031467668 | G24: =G17/G6 -> 0.022220587
A25: Revenue growth (YoY) | C25: =C6/B6-1 -> 1.1023069 | D25: =D6/C6-1 -> 0.68869275 | E25: =E6/D6-1 -> 0.71125865 | F25: =F6/E6-1 -> 0.67104177 | G25: =G6/F6-1 -> 1.6855703
A27: MEMO — OTHER EXPENSES BREAKDOWN (as disclosed)
A28: Advertisement and sales promotion | F28: 1972 | G28: 3350
A29: Delivery and related charges | E29: 3915 | F29: 5728 | G29: 9065
A30: Others | F30: 3783 | G30: 7038
A32: TIE-OUT TO REPORTED FIGURES
A33: Reported profit before tax | E33: 291 | F33: 697 | G33: 615
A34: Difference (calculated − reported) | E34: =E20-E33 -> 0 | F34: =F20-F33 -> 0 | G34: =G20-G33 -> 0
A35: Reported profit after tax | D35: -971 | E35: 351 | F35: 527 | G35: 366
A36: Difference (calculated − reported) | D36: =D22-D35 -> 0 | E36: =E22-E35 -> 0 | F36: =F22-F35 -> 0 | G36: =G22-G35 -> 0
A38: NOTES
A39: 1. Blinkit (Grofers) was consolidated from Aug-2022 (about 8 months in FY23, full year from FY24). FY23 vs FY22 is NOT like-for-like.
A40: 2. Paytm entertainment ticketing (now part of District) consolidated from 27-Aug-2024. FY25 and FY26 are not like-for-like with FY24.
A41: 3. From Q1 FY26 Blinkit moved from marketplace to inventory-led (1P). Revenue now includes full goods value, so FY26 revenue (+168.6%) is inflated; purchases of stock-in-trade jump to 32,115. Company reports like-for-like Adjusted Revenue growth of ~64-65% YoY in Q2-Q4 FY26. Use LFL/NOV in forecasts, not headline growth.
A42: 4. EBITDA here = revenue − operating expenses, excluding other income, D&A and finance cost. It INCLUDES ESOP expense and Ind AS 116 lease effects. Company "Adjusted EBITDA" adds back ESOP expense and deducts lease rentals, so the two will differ. Do not mix them.
A43: 5. FY23 and FY24 tax is backed out as PBT − reported PAT (tax line not separately read), so the PAT tie-out is zero by construction for those two years. FY25/FY26 tax is reported (current + deferred), so their tie-out is a genuine check.
A44: 6. FY25/FY26 "Other expenses" = sum of the three disclosed lines (memo rows). FY23/FY24 are the single reported total. FY24 delivery charges (3,915) is from AR FY24 MD&A; ad and others split not yet pulled.
A45: 7. Cost of materials consumed: first appears in Q3 FY26 (Blinkit Foods / Bistro). Nil in prior years.
A46: 8. TO DO: FY21 and FY22 line items (yellow). Pull from AR FY22 comparative columns on BSE (scrip 543320). Secondary sources disagree on FY22 total expenses (5,908 vs 6,205), so do not fill from aggregators.

Sheet Operating Model
A1: ETERNAL LTD. — OPERATING MODEL (₹ crore unless stated)
A2: Quarterly FY24Q4–FY26Q4: SECONDARY — HDFC Securities (HSIE) Q4FY26 results review, INR mn ÷ 10, compiled from company shareholder letters. Q1 FY27: company shareholder letter as reported in press (Business Standard, X/@NSuresh_ECW, Inc42). VERIFY against official PDFs before publishing.
A3: FY25A / FY26A = sum of four quarters. All segment figures use the company's Adjusted EBITDA definition: EBITDA + share-based payment − Ind AS 116 lease rentals.
A4: Metric | B4: Q4 FY24 | C4: Q1 FY25 | D4: Q2 FY25 | E4: Q3 FY25 | F4: Q4 FY25 | G4: Q1 FY26 | H4: Q2 FY26 | I4: Q3 FY26 | J4: Q4 FY26 | K4: Q1 FY27 | L4: FY25A | M4: FY26A | N4: Source / status
A5: NET ORDER VALUE (NOV), ₹ crore
A6: Food delivery | B6: 7189 | C6: 7928 | D6: 8281 | E6: 8443 | F6: 8210 | G6: 8967 | H6: 9423 | I6: 9846 | J6: 9757 | K6: 10769 | L6: =SUM(C6:F6) -> 32862 | M6: =SUM(G6:J6) -> 37993 | N6: HSIE table "NoV (B2C business)"; Q1 FY27 from company letter (press).
A7: Quick commerce (Blinkit) | B7: 3336 | C7: 4061 | D7: 4928 | E7: 6020 | F7: 7362 | G7: 9203 | H7: 11679 | I7: 13300 | J7: 14386 | K7: 17132 | L7: =SUM(C7:F7) -> 22371 | M7: =SUM(G7:J7) -> 48568
A8: Going-out (District) | B8: 840 | C8: 1031 | D8: 1562 | E8: 2158 | F8: 1868 | G8: 2013 | H8: 2063 | I8: 2587 | J8: 2736 | K8: 3218 | L8: =SUM(C8:F8) -> 6619 | M8: =SUM(G8:J8) -> 9399
A9: Total B2C NOV | B9: =SUM(B6:B8) -> 11365 | C9: =SUM(C6:C8) -> 13020 | D9: =SUM(D6:D8) -> 14771 | E9: =SUM(E6:E8) -> 16621 | F9: =SUM(F6:F8) -> 17440 | G9: =SUM(G6:G8) -> 20183 | H9: =SUM(H6:H8) -> 23165 | I9: =SUM(I6:I8) -> 25733 | ... M9: =SUM(M6:M8) -> 95960
A11: ADJUSTED REVENUE, ₹ crore
A12: Food delivery | B12: 2050 | C12: 2256 | D12: 2340 | E12: 2413 | F12: 2409 | G12: 2657 | H12: 2863 | I12: 3053 | J12: 3125 | K12: 3537 | L12: =SUM(C12:F12) -> 9418 | M12: =SUM(G12:J12) -> 11698
A13: Hyperpure (B2B supplies) | B13: 951 | C13: 1212 | D13: 1473 | E13: 1671 | F13: 1840 | G13: 2295 | H13: 1023 | I13: 1070 | J13: 978 | K13: 1034 | L13: =SUM(C13:F13) -> 6196 | M13: =SUM(G13:J13) -> 5366
A14: Quick commerce (Blinkit) | B14: 769 | C14: 942 | D14: 1156 | E14: 1399 | F14: 1709 | G14: 2400 | H14: 9891 | I14: 12256 | J14: 13232 | K14: 15664 | L14: =SUM(C14:F14) -> 5206 | M14: =SUM(G14:J14) -> 37779 | N14: FY25 5,206 and FY26 37,779 tie exactly to statutory quick-commerce segment revenue (Q4 FY26 filing).
A15: Going-out (District) | B15: 93 | C15: 95 | D15: 154 | E15: 259 | F15: 229 | G15: 207 | H15: 189 | I15: 300 | J15: 277 | K15: 318 | L15: =SUM(C15:F15) -> 737 | M15: =SUM(G15:J15) -> 973
A16: Others | B16: 10 | C16: 15 | D16: 4 | E16: 4 | F16: 1 | G16: 4 | H16: 2 | I16: 13 | J16: 68 | K16: 95 | L16: =SUM(C16:F16) -> 24 | M16: =SUM(G16:J16) -> 87
A17: Total adjusted revenue | B17: =SUM(B12:B16) -> 3873 | C17: =SUM(C12:C16) -> 4520 | D17: =SUM(D12:D16) -> 5127 | E17: =SUM(E12:E16) -> 5746 | F17: =SUM(F12:F16) -> 6188 | G17: =SUM(G12:G16) -> 7563 | H17: =SUM(H12:H16) -> 13968 | I17: =SUM(I12:I16) -> 16692 | ... M17: =SUM(M12:M16) -> 55903
A19: ADJUSTED EBITDA, ₹ crore
A20: Food delivery | B20: 275 | C20: 313 | D20: 341 | E20: 423 | F20: 428 | G20: 451 | H20: 503 | I20: 531 | J20: 532 | K20: 606 | L20: =SUM(C20:F20) -> 1505 | M20: =SUM(G20:J20) -> 2017
A21: Hyperpure (B2B supplies) | B21: -23 | C21: -22 | D21: -21 | E21: -19 | F21: -22 | G21: -18 | H21: -5 | I21: 1 | J21: 5 | K21: 6 | L21: =SUM(C21:F21) -> -84 | M21: =SUM(G21:J21) -> -17
A22: Quick commerce (Blinkit) | B22: -37 | C22: -3 | D22: -8 | E22: -103 | F22: -178 | G22: -162 | H22: -156 | I22: 4 | J22: 37 | K22: 102 | L22: =SUM(C22:F22) -> -292 | M22: =SUM(G22:J22) -> -277
A23: Going-out (District) | B23: -11 | C23: 10 | D23: 16 | E23: -17 | F23: -47 | G23: -54 | H23: -63 | I23: -121 | J23: -81 | K23: -65 | L23: =SUM(C23:F23) -> -38 | M23: =SUM(G23:J23) -> -319
A24: Others | B24: -10 | C24: 1 | D24: 2 | E24: 1 | F24: -16 | G24: -45 | H24: -55 | I24: -51 | J24: -64 | K24: -94 | L24: =SUM(C24:F24) -> -12 | M24: =SUM(G24:J24) -> -215
A25: Total Adjusted EBITDA (sum of segments) | B25: =SUM(B20:B24) -> 194 | C25: =SUM(C20:C24) -> 299 | D25: =SUM(D20:D24) -> 330 | E25: =SUM(E20:E24) -> 285 | F25: =SUM(F20:F24) -> 165 | G25: =SUM(G20:G24) -> 172 | H25: =SUM(H20:H24) -> 224 | I25: =SUM(I20:I24) -> 364 | ... M25: =SUM(M20:M24) -> 1189
A26: Company-reported consolidated Adj. EBITDA (check) | B26: 194 | C26: 299 | D26: 330 | E26: 285 | F26: 165 | G26: 172 | H26: 224 | I26: 364 | J26: 429 | K26: 555 | L26: =SUM(C26:F26) -> 1079 | M26: =SUM(G26:J26) -> 1189 | N26: HSIE "Total Adjusted EBITDA"; FY26 11,890 mn = ₹1,189 cr. Q1 FY27 ₹555 cr per company.
A27: Difference (sum of segments − reported) | B27: =B25-B26 -> 0 | C27: =C25-C26 -> 0 | D27: =D25-D26 -> 0 | E27: =E25-E26 -> 0 | F27: =F25-F26 -> 0 | G27: =G25-G26 -> 0 | H27: =H25-H26 -> 0 | I27: =I25-I26 -> 0 | ... M27: =M25-M26 -> 0
A29: MARGINS & TAKE RATES (calculated)
A30: Food delivery Adj. EBITDA % of NOV | B30: =B20/B6 -> 0.038252886 | C30: =C20/C6 -> 0.039480323 | D30: =D20/D6 -> 0.041178602 | E30: =E20/E6 -> 0.050100675 | F30: =F20/F6 -> 0.052131547 | G30: =G20/G6 -> 0.050295528 | H30: =H20/H6 -> 0.053380028 | I30: =I20/I6 -> 0.05393053 | ... M30: =M20/M6 -> 0.053088727
A31: Blinkit Adj. EBITDA % of NOV | B31: =B22/B7 -> -0.011091127 | C31: =C22/C7 -> -0.0007387343 | D31: =D22/D7 -> -0.0016233766 | E31: =E22/E7 -> -0.017109635 | F31: =F22/F7 -> -0.024178212 | G31: =G22/G7 -> -0.017602956 | H31: =H22/H7 -> -0.013357308 | I31: =I22/I7 -> 0.00030075188 | ... M31: =M22/M7 -> -0.0057033438
A32: District Adj. EBITDA % of NOV | B32: =B23/B8 -> -0.013095238 | C32: =C23/C8 -> 0.009699321 | D32: =D23/D8 -> 0.010243278 | E32: =E23/E8 -> -0.0078776645 | F32: =F23/F8 -> -0.0251606 | G32: =G23/G8 -> -0.026825633 | H32: =H23/H8 -> -0.030538051 | I32: =I23/I8 -> -0.046772323 | ... M32: =M23/M8 -> -0.033939781
A33: Food delivery take rate (adj. revenue % NOV) | B33: =B12/B6 -> 0.28515788 | C33: =C12/C6 -> 0.28456105 | D33: =D12/D6 -> 0.28257457 | E33: =E12/E6 -> 0.28579889 | F33: =F12/F6 -> 0.29342266 | G33: =G12/G6 -> 0.29630869 | H33: =H12/H6 -> 0.30383105 | I33: =I12/I6 -> 0.31007516 | ... M33: =M12/M6 -> 0.30789882
A34: Blinkit take rate (adj. revenue % NOV) | B34: =B14/B7 -> 0.23051559 | C34: =C14/C7 -> 0.23196257 | D34: =D14/D7 -> 0.23457792 | E34: =E14/E7 -> 0.23239203 | F34: =F14/F7 -> 0.23213801 | G34: =G14/G7 -> 0.26078453 | H34: =H14/H7 -> 0.8469047 | I34: =I14/I7 -> 0.92150376 | ... M34: =M14/M7 -> 0.77785785 | N34: Jumps from ~23% to ~92% in Q2 FY26 because Blinkit moved to inventory-led (1P) model — revenue now includes goods sold.
A35: District take rate (adj. revenue % NOV) | B35: =B15/B8 -> 0.11071429 | C35: =C15/C8 -> 0.09214355 | D35: =D15/D8 -> 0.098591549 | E35: =E15/E8 -> 0.12001854 | F35: =F15/F8 -> 0.12259101 | G35: =G15/G8 -> 0.10283159 | H35: =H15/H8 -> 0.091614154 | I35: =I15/I8 -> 0.11596444 | ... M35: =M15/M8 -> 0.10352165
A37: OPERATING KPIs (as disclosed; blank = not found in sources)
A38: Food delivery avg monthly transacting customers (mn) | F38: 20.9 | G38: 22.9 | I38: 24.9 | J38: 25.4 | K38: 27.2 | N38: HSIE KPI table + company letters. Q2 FY26 and Q3 FY25 not found.
A39: Blinkit avg monthly transacting customers (mn) | F39: 13.7 | G39: 16.9 | I39: 23.6 | J39: 27.2 | K39: 31.8
A40: Blinkit orders (mn) | F40: 141.7 | G40: 176.7 | I40: 243.3 | J40: 273.9 | K40: 331
A41: Blinkit net AOV (₹) | F41: 520 | G41: 521 | I41: 547 | J41: 525 | K41: 518
A42: Blinkit stores (period end) | G42: 1544 | I42: 2027 | J42: 2243 | K42: 2443 | N42: Mgmt target 3,000 dark stores by Mar-2027 (HSIE). Q1 FY26 1,544 per press.
A43: Food delivery contribution profit (₹ cr) | F43: 842 | I43: 1023 | J43: 998 | N43: HSIE KPI table (INR mn ÷ 10). Contribution = revenue − order-level variable costs (company definition).
A44: Blinkit contribution profit (₹ cr) | F44: 289 | I44: 736 | J44: 782
A45: Food delivery contribution margin (% NOV) | F45: =F43/F6 -> 0.10255786 | I45: =I43/I6 -> 0.10390006 | J45: =J43/J6 -> 0.10228554
A46: Blinkit contribution margin (% NOV) | F46: =F44/F7 -> 0.039255637 | I46: =I44/I7 -> 0.055338346 | J46: =J44/J7 -> 0.054358404
A49: RECONCILIATION — reported EBITDA → Adjusted EBITDA, and cash-flow calibration | B49: FY25A | C49: FY26A | D49: Source / status
A50: EBITDA excl. other income (Historical sheet) | B50: =Historical!F17 -> 637 | C50: =Historical!G17 -> 1208
A51: Add: share-based payment expense | B51: 798 | C51: 819 | D51: REPORTED: segment note, Q4 FY26 consolidated results (Note 3 reconciliation).
A52: EBITDA before SBC (= total segment results) | B52: =B50+B51 -> 1435 | C52: =C50+C51 -> 2027
A53: Reported total segment results (tie-out) | B53: 1435 | C53: 2027 | D53: REPORTED: segment results total, Q4 FY26 filing. Difference row below should be zero.
A54: Difference | B54: =B52-B53 -> 0 | C54: =C52-C53 -> 0
A55: Less: Ind AS 116 lease rentals (derived plug) | B55: =B52-B56 -> 356 | C55: =C52-C56 -> 838 | D55: DERIVED. FY26 plug equals cash lease payments exactly (838), confirming the bridge. FY25 differs by 49 (definition/timing) — flagged, not forced.
A56: Adjusted EBITDA (sum of segments) | B56: =L25 -> 1079 | C56: =M25 -> 1189
A57: Memo: lease principal paid (cash flow statement) | B57: 258 | C57: 471 | D57: REPORTED: consolidated cash flow statement, Q4 FY26 filing (FY25 comparative).
A58: Memo: lease interest paid (cash flow statement) | B58: 147 | C58: 367
A59: Memo: total cash lease payments | B59: =B57+B58 -> 405 | C59: =C57+C58 -> 838
A60: Plug minus cash lease payments | B60: =B55-B59 -> -49 | C60: =C55-C59 -> 0
A62: Cash-flow calibration (consolidated, reported)
A63: Net cash from operating activities | B63: 308 | C63: 632
A64: Capex (PPE & intangibles incl. CWIP/advances) | B64: 936 | C64: 1751
A65: Total D&A (Historical sheet) | B65: =Historical!F18 -> 863 | C65: =Historical!G18 -> 1597
A66: D&A excl. ROU (proxy = total D&A − lease principal paid) | B66: =B65-B57 -> 605 | C66: =C65-C57 -> 1126
A67: Working-capital movement (sum of CF lines) | B67: -1093 | C67: -1228 | D67: REPORTED lines summed: receivables, other fin. assets, other assets, inventories, other liabilities, provisions, payables.
A68: B2C NOV (from table above) | B68: =L9 -> 61852 | C68: =M9 -> 95960
A69: SBC % of B2C NOV | B69: =B51/B68 -> 0.012901766 | C69: =C51/C68 -> 0.0085348062
A70: Capex % of B2C NOV | B70: =B64/B68 -> 0.015132898 | C70: =C64/C68 -> 0.018247186
A71: D&A excl. ROU % of B2C NOV | B71: =B66/B68 -> 0.0097814137 | C71: =C66/C68 -> 0.011734056
A72: Working-capital outflow % of incremental B2C NOV | C72: =-C67/(C68-B68) -> 0.036003284 | D72: FY26 outflow was elevated by the 1P transition (inventory build, seller settlements). Model assumes 1.0% — a judgement call; sensitivity is small relative to EV.
A75: ="FORECAST — segment operating model | scenario: "&Assumptions!B32 -> FORECAST — segment operating model | scenario: Base
A76: Fiscal year | B76: FY25A | C76: FY26A | D76: FY27E | E76: FY28E | F76: FY29E | G76: FY30E | H76: FY31E | I76: FY32E | J76: FY33E | K76: FY34E | L76: FY35E | M76: FY36E
A77: Forecast year index (t) | C77: 0 | D77: =C77+1 -> 1 | E77: =D77+1 -> 2 | F77: =E77+1 -> 3 | G77: =F77+1 -> 4 | H77: =G77+1 -> 5 | I77: =H77+1 -> 6 | J77: =I77+1 -> 7 | K77: =J77+1 -> 8 | ... M77: =L77+1 -> 10
A78: FOOD DELIVERY (Zomato)
A79: NOV | B79: =L6 -> 32862 | C79: =M6 -> 37993 | D79: =C79*(1+D80) -> 45591.6 | E79: =D79*(1+E80) -> 54102.032 | F79: =E79*(1+F80) -> 63479.718 | G79: =F79*(1+G80) -> 73636.472 | H79: =G79*(1+H80) -> 84436.488 | I79: =H79*(1+I80) -> 95694.687 | J79: =I79*(1+J80) -> 107178.05 | K79: =J79*(1+K80) -> 118610.37 | ... M79: =L79*(1+M80) -> 140055.13
A80: NOV growth (YoY) | C80: =C79/B79-1 -> 0.15613779 | D80: =Assumptions!$B$36+(Assumptions!$B$37-Assumptions!$B$36)*(D$77-1)/9 -> 0.2 | E80: =Assumptions!$B$36+(Assumptions!$B$37-Assumptions!$B$36)*(E$77-1)/9 -> 0.18666667 | F80: =Assumptions!$B$36+(Assumptions!$B$37-Assumptions!$B$36)*(F$77-1)/9 -> 0.17333333 | G80: =Assumptions!$B$36+(Assumptions!$B$37-Assumptions!$B$36)*(G$77-1)/9 -> 0.16 | H80: =Assumptions!$B$36+(Assumptions!$B$37-Assumptions!$B$36)*(H$77-1)/9 -> 0.14666667 | I80: =Assumptions!$B$36+(Assumptions!$B$37-Assumptions!$B$36)*(I$77-1)/9 -> 0.13333333 | J80: =Assumptions!$B$36+(Assumptions!$B$37-Assumptions!$B$36)*(J$77-1)/9 -> 0.12 | K80: =Assumptions!$B$36+(Assumptions!$B$37-Assumptions!$B$36)*(K$77-1)/9 -> 0.10666667 | ... M80: =Assumptions!$B$36+(Assumptions!$B$37-Assumptions!$B$36)*(M$77-1)/9 -> 0.08
A81: Adj. EBITDA margin (% of NOV) | B81: =B82/B79 -> 0.045797578 | C81: =C82/C79 -> 0.053088727 | D81: =$C81+(Assumptions!$B$38-$C81)*MIN(1,D$77/Assumptions!$B$39) -> 0.055392485 | E81: =$C81+(Assumptions!$B$38-$C81)*MIN(1,E$77/Assumptions!$B$39) -> 0.057696242 | F81: =$C81+(Assumptions!$B$38-$C81)*MIN(1,F$77/Assumptions!$B$39) -> 0.06 | G81: =$C81+(Assumptions!$B$38-$C81)*MIN(1,G$77/Assumptions!$B$39) -> 0.06 | H81: =$C81+(Assumptions!$B$38-$C81)*MIN(1,H$77/Assumptions!$B$39) -> 0.06 | I81: =$C81+(Assumptions!$B$38-$C81)*MIN(1,I$77/Assumptions!$B$39) -> 0.06 | J81: =$C81+(Assumptions!$B$38-$C81)*MIN(1,J$77/Assumptions!$B$39) -> 0.06 | K81: =$C81+(Assumptions!$B$38-$C81)*MIN(1,K$77/Assumptions!$B$39) -> 0.06 | ... M81: =$C81+(Assumptions!$B$38-$C81)*MIN(1,M$77/Assumptions!$B$39) -> 0.06
A82: Adj. EBITDA | B82: =L20 -> 1505 | C82: =M20 -> 2017 | D82: =D79*D81 -> 2525.432 | E82: =E79*E81 -> 3121.4839 | F82: =F79*F81 -> 3808.7831 | G82: =G79*G81 -> 4418.1883 | H82: =H79*H81 -> 5066.1893 | I82: =I79*I81 -> 5741.6812 | J82: =J79*J81 -> 6430.6829 | K82: =K79*K81 -> 7116.6225 | ... M82: =M79*M81 -> 8403.3078
A83: Adjusted revenue | B83: =L12 -> 9418 | C83: =M12 -> 11698 | D83: =D79*Assumptions!$B$40 -> 14817.27 | E83: =E79*Assumptions!$B$40 -> 17583.16 | F83: =F79*Assumptions!$B$40 -> 20630.908 | G83: =G79*Assumptions!$B$40 -> 23931.854 | H83: =H79*Assumptions!$B$40 -> 27441.859 | I83: =I79*Assumptions!$B$40 -> 31100.773 | J83: =J79*Assumptions!$B$40 -> 34832.866 | K83: =K79*Assumptions!$B$40 -> 38548.372 | ... M83: =M79*Assumptions!$B$40 -> 45517.917
A85: QUICK COMMERCE (Blinkit)
A86: NOV | B86: =L7 -> 22371 | C86: =M7 -> 48568 | D86: =C86*(1+D87) -> 82565.6 | E86: =D86*(1+E87) -> 134490.19 | F86: =E86*(1+F87) -> 209505.83 | G86: =F86*(1+G87) -> 311465.33 | H86: =G86*(1+H87) -> 440896.48 | I86: =H86*(1+I87) -> 592760.82 | J86: =I86*(1+J87) -> 754782.11 | K86: =J86*(1+K87) -> 907415.83 | ... M86: =L86*(1+M87) -> 1087971.4
A87: NOV growth (YoY) | C87: =C86/B86-1 -> 1.171025 | D87: =Assumptions!$B$42+(Assumptions!$B$43-Assumptions!$B$42)*(D$77-1)/9 -> 0.7 | E87: =Assumptions!$B$42+(Assumptions!$B$43-Assumptions!$B$42)*(E$77-1)/9 -> 0.62888889 | F87: =Assumptions!$B$42+(Assumptions!$B$43-Assumptions!$B$42)*(F$77-1)/9 -> 0.55777778 | G87: =Assumptions!$B$42+(Assumptions!$B$43-Assumptions!$B$42)*(G$77-1)/9 -> 0.48666667 | H87: =Assumptions!$B$42+(Assumptions!$B$43-Assumptions!$B$42)*(H$77-1)/9 -> 0.41555556 | I87: =Assumptions!$B$42+(Assumptions!$B$43-Assumptions!$B$42)*(I$77-1)/9 -> 0.34444444 | J87: =Assumptions!$B$42+(Assumptions!$B$43-Assumptions!$B$42)*(J$77-1)/9 -> 0.27333333 | K87: =Assumptions!$B$42+(Assumptions!$B$43-Assumptions!$B$42)*(K$77-1)/9 -> 0.20222222 | ... M87: =Assumptions!$B$42+(Assumptions!$B$43-Assumptions!$B$42)*(M$77-1)/9 -> 0.06
A88: Adj. EBITDA margin (% of NOV) | B88: =B89/B86 -> -0.013052613 | C88: =C89/C86 -> -0.0057033438 | D88: =$C88+(Assumptions!$B$44-$C88)*MIN(1,D$77/Assumptions!$B$45) -> 0.005437325 | E88: =$C88+(Assumptions!$B$44-$C88)*MIN(1,E$77/Assumptions!$B$45) -> 0.016577994 | F88: =$C88+(Assumptions!$B$44-$C88)*MIN(1,F$77/Assumptions!$B$45) -> 0.027718662 | G88: =$C88+(Assumptions!$B$44-$C88)*MIN(1,G$77/Assumptions!$B$45) -> 0.038859331 | H88: =$C88+(Assumptions!$B$44-$C88)*MIN(1,H$77/Assumptions!$B$45) -> 0.05 | I88: =$C88+(Assumptions!$B$44-$C88)*MIN(1,I$77/Assumptions!$B$45) -> 0.05 | J88: =$C88+(Assumptions!$B$44-$C88)*MIN(1,J$77/Assumptions!$B$45) -> 0.05 | K88: =$C88+(Assumptions!$B$44-$C88)*MIN(1,K$77/Assumptions!$B$45) -> 0.05 | ... M88: =$C88+(Assumptions!$B$44-$C88)*MIN(1,M$77/Assumptions!$B$45) -> 0.05
A89: Adj. EBITDA | B89: =L22 -> -292 | C89: =M22 -> -277 | D89: =D86*D88 -> 448.936 | E89: =E86*E88 -> 2229.5775 | F89: =F86*F88 -> 5807.2213 | G89: =G86*G88 -> 12103.334 | H89: =H86*H88 -> 22044.824 | I89: =I86*I88 -> 29638.041 | J89: =J86*J88 -> 37739.106 | K89: =K86*K88 -> 45370.791 | ... M89: =M86*M88 -> 54398.571
A90: Adjusted revenue | B90: =L14 -> 5206 | C90: =M14 -> 37779 | D90: =D86*Assumptions!$B$46 -> 75960.352 | E90: =E86*Assumptions!$B$46 -> 123730.97 | F90: =F86*Assumptions!$B$46 -> 192745.36 | G90: =G86*Assumptions!$B$46 -> 286548.1 | H90: =H86*Assumptions!$B$46 -> 405624.76 | I90: =I86*Assumptions!$B$46 -> 545339.95 | J90: =J86*Assumptions!$B$46 -> 694399.54 | K90: =K86*Assumptions!$B$46 -> 834822.56 | ... M90: =M86*Assumptions!$B$46 -> 1000933.7
A92: GOING-OUT (District)
A93: NOV | B93: =L8 -> 6619 | C93: =M8 -> 9399 | D93: =C93*(1+D94) -> 13158.6 | E93: =D93*(1+E94) -> 17939.558 | F93: =E93*(1+F94) -> 23799.814 | G93: =F93*(1+G94) -> 30701.76 | H93: =G93*(1+H94) -> 38479.539 | I93: =H93*(1+I94) -> 46816.772 | J93: =I93*(1+J94) -> 55243.791 | K93: =J93*(1+K94) -> 63162.068 | ... M93: =L93*(1+M94) -> 74792.31
A94: NOV growth (YoY) | C94: =C93/B93-1 -> 0.42000302 | D94: =Assumptions!$B$48+(Assumptions!$B$49-Assumptions!$B$48)*(D$77-1)/9 -> 0.4 | E94: =Assumptions!$B$48+(Assumptions!$B$49-Assumptions!$B$48)*(E$77-1)/9 -> 0.36333333 | F94: =Assumptions!$B$48+(Assumptions!$B$49-Assumptions!$B$48)*(F$77-1)/9 -> 0.32666667 | G94: =Assumptions!$B$48+(Assumptions!$B$49-Assumptions!$B$48)*(G$77-1)/9 -> 0.29 | H94: =Assumptions!$B$48+(Assumptions!$B$49-Assumptions!$B$48)*(H$77-1)/9 -> 0.25333333 | I94: =Assumptions!$B$48+(Assumptions!$B$49-Assumptions!$B$48)*(I$77-1)/9 -> 0.21666667 | J94: =Assumptions!$B$48+(Assumptions!$B$49-Assumptions!$B$48)*(J$77-1)/9 -> 0.18 | K94: =Assumptions!$B$48+(Assumptions!$B$49-Assumptions!$B$48)*(K$77-1)/9 -> 0.14333333 | ... M94: =Assumptions!$B$48+(Assumptions!$B$49-Assumptions!$B$48)*(M$77-1)/9 -> 0.07
A95: Adj. EBITDA margin (% of NOV) | B95: =B96/B93 -> -0.0057410485 | C95: =C96/C93 -> -0.033939781 | D95: =$C95+(Assumptions!$B$50-$C95)*MIN(1,D$77/Assumptions!$B$51) -> -0.019151825 | E95: =$C95+(Assumptions!$B$50-$C95)*MIN(1,E$77/Assumptions!$B$51) -> -0.0043638685 | F95: =$C95+(Assumptions!$B$50-$C95)*MIN(1,F$77/Assumptions!$B$51) -> 0.010424088 | G95: =$C95+(Assumptions!$B$50-$C95)*MIN(1,G$77/Assumptions!$B$51) -> 0.025212044 | H95: =$C95+(Assumptions!$B$50-$C95)*MIN(1,H$77/Assumptions!$B$51) -> 0.04 | I95: =$C95+(Assumptions!$B$50-$C95)*MIN(1,I$77/Assumptions!$B$51) -> 0.04 | J95: =$C95+(Assumptions!$B$50-$C95)*MIN(1,J$77/Assumptions!$B$51) -> 0.04 | K95: =$C95+(Assumptions!$B$50-$C95)*MIN(1,K$77/Assumptions!$B$51) -> 0.04 | ... M95: =$C95+(Assumptions!$B$50-$C95)*MIN(1,M$77/Assumptions!$B$51) -> 0.04
A96: Adj. EBITDA | B96: =L23 -> -38 | C96: =M23 -> -319 | D96: =D93*D95 -> -252.0112 | E96: =E93*E95 -> -78.285872 | F96: =F93*F95 -> 248.09134 | G96: =G93*G95 -> 774.05411 | H96: =H93*H95 -> 1539.1815 | I96: =I93*I95 -> 1872.6709 | J96: =J93*J95 -> 2209.7516 | K96: =K93*K95 -> 2526.4827 | ... M96: =M93*M95 -> 2991.6924
A97: Adjusted revenue | B97: =L15 -> 737 | C97: =M15 -> 973 | D97: =D93*Assumptions!$B$52 -> 1381.653 | E97: =E93*Assumptions!$B$52 -> 1883.6536 | F97: =F93*Assumptions!$B$52 -> 2498.9804 | G97: =G93*Assumptions!$B$52 -> 3223.6848 | H97: =H93*Assumptions!$B$52 -> 4040.3516 | I97: =I93*Assumptions!$B$52 -> 4915.7611 | J97: =J93*Assumptions!$B$52 -> 5800.5981 | K97: =K93*Assumptions!$B$52 -> 6632.0171 | ... M97: =M93*Assumptions!$B$52 -> 7853.1925
A99: HYPERPURE (B2B supplies)
A100: Revenue | B100: =L13 -> 6196 | C100: =M13 -> 5366 | D100: =Assumptions!$B$54 -> 4400 | E100: =D100*(1+E101) -> 5368 | F100: =E100*(1+F101) -> 6448.31 | G100: =F100*(1+G101) -> 7625.1266 | H100: =G100*(1+H101) -> 8873.7411 | I100: =H100*(1+I101) -> 10160.434 | J100: =I100*(1+J101) -> 11443.188 | K100: =J100*(1+K101) -> 12673.331 | L100: =K100*(1+L101) -> 13798.089 | M100: =L100*(1+M101) -> 14763.955
A101: Revenue growth (YoY) | C101: =C100/B100-1 -> -0.13395739 | D101: =D100/C100-1 -> -0.18002236 | E101: =Assumptions!$B$55+(Assumptions!$B$56-Assumptions!$B$55)*(E$77-2)/8 -> 0.22 | F101: =Assumptions!$B$55+(Assumptions!$B$56-Assumptions!$B$55)*(F$77-2)/8 -> 0.20125 | G101: =Assumptions!$B$55+(Assumptions!$B$56-Assumptions!$B$55)*(G$77-2)/8 -> 0.1825 | H101: =Assumptions!$B$55+(Assumptions!$B$56-Assumptions!$B$55)*(H$77-2)/8 -> 0.16375 | I101: =Assumptions!$B$55+(Assumptions!$B$56-Assumptions!$B$55)*(I$77-2)/8 -> 0.145 | J101: =Assumptions!$B$55+(Assumptions!$B$56-Assumptions!$B$55)*(J$77-2)/8 -> 0.12625 | K101: =Assumptions!$B$55+(Assumptions!$B$56-Assumptions!$B$55)*(K$77-2)/8 -> 0.1075 | L101: =Assumptions!$B$55+(Assumptions!$B$56-Assumptions!$B$55)*(L$77-2)/8 -> 0.08875 | M101: =Assumptions!$B$55+(Assumptions!$B$56-Assumptions!$B$55)*(M$77-2)/8 -> 0.07 | N101: FY27E growth is negative only because FY26 included non-restaurant sales later moved to Blinkit (1P). Not like-for-like.
A102: Adj. EBITDA margin (% of revenue) | B102: =B103/B100 -> -0.013557134 | C102: =C103/C100 -> -0.0031680954 | D102: =Assumptions!$B$57 -> 0.005 | E102: =$D102+(Assumptions!$B$58-$D102)*MIN(1,(E$77-1)/(Assumptions!$B$59-1)) -> 0.0075 | F102: =$D102+(Assumptions!$B$58-$D102)*MIN(1,(F$77-1)/(Assumptions!$B$59-1)) -> 0.01 | G102: =$D102+(Assumptions!$B$58-$D102)*MIN(1,(G$77-1)/(Assumptions!$B$59-1)) -> 0.0125 | H102: =$D102+(Assumptions!$B$58-$D102)*MIN(1,(H$77-1)/(Assumptions!$B$59-1)) -> 0.015 | I102: =$D102+(Assumptions!$B$58-$D102)*MIN(1,(I$77-1)/(Assumptions!$B$59-1)) -> 0.015 | J102: =$D102+(Assumptions!$B$58-$D102)*MIN(1,(J$77-1)/(Assumptions!$B$59-1)) -> 0.015 | K102: =$D102+(Assumptions!$B$58-$D102)*MIN(1,(K$77-1)/(Assumptions!$B$59-1)) -> 0.015 | L102: =$D102+(Assumptions!$B$58-$D102)*MIN(1,(L$77-1)/(Assumptions!$B$59-1)) -> 0.015 | M102: =$D102+(Assumptions!$B$58-$D102)*MIN(1,(M$77-1)/(Assumptions!$B$59-1)) -> 0.015
A103: Adj. EBITDA | B103: =L21 -> -84 | C103: =M21 -> -17 | D103: =D100*D102 -> 22 | E103: =E100*E102 -> 40.26 | F103: =F100*F102 -> 64.4831 | G103: =G100*G102 -> 95.314082 | H103: =H100*H102 -> 133.10612 | I103: =I100*I102 -> 152.4065 | J103: =J100*J102 -> 171.64782 | K103: =K100*K102 -> 190.09996 | ... M103: =M100*M102 -> 221.45933
A105: CONSOLIDATED
A106: Total B2C NOV | B106: =B79+B86+B93 -> 61852 | C106: =C79+C86+C93 -> 95960 | D106: =D79+D86+D93 -> 141315.8 | E106: =E79+E86+E93 -> 206531.78 | F106: =F79+F86+F93 -> 296785.36 | G106: =G79+G86+G93 -> 415803.56 | H106: =H79+H86+H93 -> 563812.5 | I106: =I79+I86+I93 -> 735272.28 | ... M106: =M79+M86+M93 -> 1302818.9
A107: B2C NOV growth | C107: =C106/B106-1 -> 0.55144539 | D107: =D106/C106-1 -> 0.47265319 | E107: =E106/D106-1 -> 0.46149106 | F107: =F106/E106-1 -> 0.43699609 | G107: =G106/F106-1 -> 0.40102451 | H107: =H106/G106-1 -> 0.35595882 | I107: =I106/H106-1 -> 0.30410779 | J107: =J106/I106-1 -> 0.24743442 | ... M107: =M106/L106-1 -> 0.06268572
A108: Adjusted revenue | B108: =B83+B90+B97+B100+B117 -> 21581 | C108: =C83+C90+C97+C100+C117 -> 55903 | D108: =D83+D90+D97+D100+D117 -> 96983.222 | E108: =E83+E90+E97+E100+E117 -> 149185.38 | F108: =F83+F90+F97+F100+F117 -> 223213.92 | G108: =G83+G90+G97+G100+G117 -> 322576.18 | H108: =H83+H90+H97+H100+H117 -> 447672.15 | I108: =I83+I90+I97+I100+I117 -> 593722.74 | ... M108: =M83+M90+M97+M100+M117 -> 1072977.2
A109: Adjusted revenue growth | C109: =C108/B108-1 -> 1.5903804 | D109: =D108/C108-1 -> 0.73484826 | E109: =E108/D108-1 -> 0.5382597 | F109: =F108/E108-1 -> 0.49621841 | G109: =G108/F108-1 -> 0.44514368 | H109: =H108/G108-1 -> 0.38780287 | I109: =I108/H108-1 -> 0.32624453 | J109: =J108/I108-1 -> 0.2619153 | ... M109: =M108/L108-1 -> 0.06105235
A110: Adjusted EBITDA | B110: =B82+B89+B96+B103+B116 -> 1079 | C110: =C82+C89+C96+C103+C116 -> 1189 | D110: =D82+D89+D96+D103+D116 -> 2391.0673 | E110: =E82+E89+E96+E103+E116 -> 4796.7061 | F110: =F82+F89+F96+F103+F116 -> 9186.6154 | G110: =G82+G89+G96+G103+G116 -> 16351.382 | H110: =H82+H89+H96+H103+H116 -> 27373.77 | I110: =I82+I89+I96+I103+I116 -> 35566.619 | ... M110: =M82+M89+M96+M103+M116 -> 62757.983 | N110: Check vs management: "$1 bn Adj. EBITDA hopefully by FY29" (Q4 FY26 letter). See US$ row, FY29E column.
A111: Adj. EBITDA margin (% of B2C NOV) | B111: =B110/B106 -> 0.017444868 | C111: =C110/C106 -> 0.012390579 | D111: =D110/D106 -> 0.016920028 | E111: =E110/E106 -> 0.023225027 | F111: =F110/F106 -> 0.030953735 | G111: =G110/G106 -> 0.039324776 | H111: =H110/H106 -> 0.048551193 | I111: =I110/I106 -> 0.048372038 | ... M111: =M110/M106 -> 0.04817092
A112: Adj. EBITDA margin (% of adjusted revenue) | B112: =B110/B108 -> 0.049997683 | C112: =C110/C108 -> 0.021268984 | D112: =D110/D108 -> 0.024654443 | E112: =E110/E108 -> 0.032152655 | F112: =F110/F108 -> 0.041156105 | G112: =G110/G108 -> 0.050689986 | H112: =H110/H108 -> 0.061146912 | I112: =I110/I108 -> 0.059904424 | ... M112: =M110/M108 -> 0.058489576
A113: Adj. EBITDA (US$ mn, cross-check) | B113: =B110*10/Assumptions!$B$28 -> 114.0592 | C113: =C110*10/Assumptions!$B$28 -> 125.6871 | D113: =D110*10/Assumptions!$B$28 -> 252.75553 | E113: =E110*10/Assumptions!$B$28 -> 507.05139 | F113: =F110*10/Assumptions!$B$28 -> 971.10099 | G113: =G110*10/Assumptions!$B$28 -> 1728.4759 | H113: =H110*10/Assumptions!$B$28 -> 2893.6331 | I113: =I110*10/Assumptions!$B$28 -> 3759.6849 | ... M113: =M110*10/Assumptions!$B$28 -> 6634.0362
...

Sheet Valuation
A1: ETERNAL LTD. — VALUATION (₹ crore unless stated)
A2: ="DCF & SOTP | active scenario: "&Assumptions!B32&" | valuation date "&TEXT(Assumptions!B25,"dd-mmm-yyyy") -> DCF & SOTP | active scenario: Base | valuation date 30-Jun-2026
A3: Basis: pre-Ind AS 116 (lease rent is inside Adjusted EBITDA; lease liabilities excluded from debt). SBC deducted as a real cost. Cash flows exclude treasury income (cash is added in the equity bridge).
A4: DISCOUNTED CASH FLOW | C4: FY26A | D4: FY27E | E4: FY28E | F4: FY29E | G4: FY30E | H4: FY31E | I4: FY32E | J4: FY33E | K4: FY34E | L4: FY35E | M4: FY36E
A5: B2C NOV | C5: ='Operating Model'!C106 -> 95960 | D5: ='Operating Model'!D106 -> 141315.8 | E5: ='Operating Model'!E106 -> 206531.78 | F5: ='Operating Model'!F106 -> 296785.36 | G5: ='Operating Model'!G106 -> 415803.56 | H5: ='Operating Model'!H106 -> 563812.5 | I5: ='Operating Model'!I106 -> 735272.28 | J5: ='Operating Model'!J106 -> 917203.95 | ... M5: ='Operating Model'!M106 -> 1302818.9
A6: Adjusted revenue | C6: ='Operating Model'!C108 -> 55903 | D6: ='Operating Model'!D108 -> 96983.222 | E6: ='Operating Model'!E108 -> 149185.38 | F6: ='Operating Model'!F108 -> 223213.92 | G6: ='Operating Model'!G108 -> 322576.18 | H6: ='Operating Model'!H108 -> 447672.15 | I6: ='Operating Model'!I108 -> 593722.74 | J6: ='Operating Model'!J108 -> 749227.81 | ... M6: ='Operating Model'!M108 -> 1072977.2
A7: Adjusted EBITDA (pre-SBC, post lease rent) | C7: ='Operating Model'!C110 -> 1189 | D7: ='Operating Model'!D110 -> 2391.0673 | E7: ='Operating Model'!E110 -> 4796.7061 | F7: ='Operating Model'!F110 -> 9186.6154 | G7: ='Operating Model'!G110 -> 16351.382 | H7: ='Operating Model'!H110 -> 27373.77 | I7: ='Operating Model'!I110 -> 35566.619 | J7: ='Operating Model'!J110 -> 44258.178 | ... M7: ='Operating Model'!M110 -> 62757.983
A8: SBC (% of B2C NOV) | D8: =Assumptions!$B$64+(Assumptions!$B$65-Assumptions!$B$64)*('Operating Model'!D$77-1)/9 -> 0.0085 | E8: =Assumptions!$B$64+(Assumptions!$B$65-Assumptions!$B$64)*('Operating Model'!E$77-1)/9 -> 0.0081111111 | F8: =Assumptions!$B$64+(Assumptions!$B$65-Assumptions!$B$64)*('Operating Model'!F$77-1)/9 -> 0.0077222222 | G8: =Assumptions!$B$64+(Assumptions!$B$65-Assumptions!$B$64)*('Operating Model'!G$77-1)/9 -> 0.0073333333 | H8: =Assumptions!$B$64+(Assumptions!$B$65-Assumptions!$B$64)*('Operating Model'!H$77-1)/9 -> 0.0069444444 | I8: =Assumptions!$B$64+(Assumptions!$B$65-Assumptions!$B$64)*('Operating Model'!I$77-1)/9 -> 0.0065555556 | J8: =Assumptions!$B$64+(Assumptions!$B$65-Assumptions!$B$64)*('Operating Model'!J$77-1)/9 -> 0.0061666667 | K8: =Assumptions!$B$64+(Assumptions!$B$65-Assumptions!$B$64)*('Operating Model'!K$77-1)/9 -> 0.0057777778 | ... M8: =Assumptions!$B$64+(Assumptions!$B$65-Assumptions!$B$64)*('Operating Model'!M$77-1)/9 -> 0.005
A9: Less: share-based payment | D9: =-D5*D8 -> -1201.1843 | E9: =-E5*E8 -> -1675.2022 | F9: =-F5*F8 -> -2291.8425 | G9: =-G5*G8 -> -3049.2261 | H9: =-H5*H8 -> -3915.3646 | I9: =-I5*I8 -> -4820.1183 | J9: =-J5*J8 -> -5656.091 | K9: =-K5*K8 -> -6293.0878 | ... M9: =-M5*M8 -> -6514.0943
A10: EBITDA after SBC | D10: =D7+D9 -> 1189.883 | E10: =E7+E9 -> 3121.5039 | F10: =F7+F9 -> 6894.7729 | G10: =G7+G9 -> 13302.156 | H10: =H7+H9 -> 23458.405 | I10: =I7+I9 -> 30746.501 | J10: =J7+J9 -> 38602.087 | K10: =K7+K9 -> 46187.938 | ... M10: =M7+M9 -> 56243.889
A11: D&A excl. ROU (% of B2C NOV) | D11: =Assumptions!$B$68+(Assumptions!$B$69-Assumptions!$B$68)*('Operating Model'!D$77-1)/9 -> 0.012 | E11: =Assumptions!$B$68+(Assumptions!$B$69-Assumptions!$B$68)*('Operating Model'!E$77-1)/9 -> 0.011888889 | F11: =Assumptions!$B$68+(Assumptions!$B$69-Assumptions!$B$68)*('Operating Model'!F$77-1)/9 -> 0.011777778 | G11: =Assumptions!$B$68+(Assumptions!$B$69-Assumptions!$B$68)*('Operating Model'!G$77-1)/9 -> 0.011666667 | H11: =Assumptions!$B$68+(Assumptions!$B$69-Assumptions!$B$68)*('Operating Model'!H$77-1)/9 -> 0.011555556 | I11: =Assumptions!$B$68+(Assumptions!$B$69-Assumptions!$B$68)*('Operating Model'!I$77-1)/9 -> 0.011444444 | J11: =Assumptions!$B$68+(Assumptions!$B$69-Assumptions!$B$68)*('Operating Model'!J$77-1)/9 -> 0.011333333 | K11: =Assumptions!$B$68+(Assumptions!$B$69-Assumptions!$B$68)*('Operating Model'!K$77-1)/9 -> 0.011222222 | ... M11: =Assumptions!$B$68+(Assumptions!$B$69-Assumptions!$B$68)*('Operating Model'!M$77-1)/9 -> 0.011
A12: Less: D&A | D12: =-D5*D11 -> -1695.7896 | E12: =-E5*E11 -> -2455.4334 | F12: =-F5*F11 -> -3495.472 | G12: =-G5*G11 -> -4851.0415 | H12: =-H5*H11 -> -6515.1667 | I12: =-I5*I11 -> -8414.7827 | J12: =-J5*J11 -> -10394.978 | K12: =-K5*K11 -> -12223.113 | ... M12: =-M5*M11 -> -14331.007
A13: EBIT | D13: =D10+D12 -> -505.9066 | E13: =E10+E12 -> 666.07056 | F13: =F10+F12 -> 3399.3009 | G13: =G10+G12 -> 8451.1144 | H13: =H10+H12 -> 16943.238 | I13: =I10+I12 -> 22331.718 | J13: =J10+J12 -> 28207.109 | K13: =K10+K12 -> 33964.825 | ... M13: =M10+M12 -> 41912.881
A14: EBIT margin (% of adjusted revenue) | D14: =D13/D6 -> -0.0052164342 | E14: =E13/E6 -> 0.0044647173 | F14: =F13/F6 -> 0.015228893 | G14: =G13/G6 -> 0.026198817 | H14: =H13/H6 -> 0.037847425 | I14: =I13/I6 -> 0.037613041 | J14: =J13/J6 -> 0.037648241 | K14: =K13/K6 -> 0.037909547 | ... M14: =M13/M6 -> 0.039062229
A15: Tax rate on EBIT | D15: =Assumptions!$B$12 -> 0.2517 | E15: =Assumptions!$B$12 -> 0.2517 | F15: =Assumptions!$B$12 -> 0.2517 | G15: =Assumptions!$B$12 -> 0.2517 | H15: =Assumptions!$B$12 -> 0.2517 | I15: =Assumptions!$B$12 -> 0.2517 | J15: =Assumptions!$B$12 -> 0.2517 | K15: =Assumptions!$B$12 -> 0.2517 | ... M15: =Assumptions!$B$12 -> 0.2517
A16: Less: tax on EBIT (nil if EBIT < 0) | D16: =-MAX(0,D13)*D15 -> 0 | E16: =-MAX(0,E13)*E15 -> -167.64996 | F16: =-MAX(0,F13)*F15 -> -855.60404 | G16: =-MAX(0,G13)*G15 -> -2127.1455 | H16: =-MAX(0,H13)*H15 -> -4264.6131 | I16: =-MAX(0,I13)*I15 -> -5620.8934 | J16: =-MAX(0,J13)*J15 -> -7099.7293 | K16: =-MAX(0,K13)*K15 -> -8548.9465 | ... M16: =-MAX(0,M13)*M15 -> -10549.472
A17: NOPAT | D17: =D13+D16 -> -505.9066 | E17: =E13+E16 -> 498.4206 | F17: =F13+F16 -> 2543.6969 | G17: =G13+G16 -> 6323.9689 | H17: =H13+H16 -> 12678.625 | I17: =I13+I16 -> 16710.824 | J17: =J13+J16 -> 21107.38 | K17: =K13+K16 -> 25415.879 | ... M17: =M13+M16 -> 31363.409
A18: Add: D&A | D18: =-D12 -> 1695.7896 | E18: =-E12 -> 2455.4334 | F18: =-F12 -> 3495.472 | G18: =-G12 -> 4851.0415 | H18: =-H12 -> 6515.1667 | I18: =-I12 -> 8414.7827 | J18: =-J12 -> 10394.978 | K18: =-K12 -> 12223.113 | ... M18: =-M12 -> 14331.007
A19: Capex (% of B2C NOV) | D19: =Assumptions!$B$66+(Assumptions!$B$67-Assumptions!$B$66)*('Operating Model'!D$77-1)/9 -> 0.018 | E19: =Assumptions!$B$66+(Assumptions!$B$67-Assumptions!$B$66)*('Operating Model'!E$77-1)/9 -> 0.017333333 | F19: =Assumptions!$B$66+(Assumptions!$B$67-Assumptions!$B$66)*('Operating Model'!F$77-1)/9 -> 0.016666667 | G19: =Assumptions!$B$66+(Assumptions!$B$67-Assumptions!$B$66)*('Operating Model'!G$77-1)/9 -> 0.016 | H19: =Assumptions!$B$66+(Assumptions!$B$67-Assumptions!$B$66)*('Operating Model'!H$77-1)/9 -> 0.015333333 | I19: =Assumptions!$B$66+(Assumptions!$B$67-Assumptions!$B$66)*('Operating Model'!I$77-1)/9 -> 0.014666667 | J19: =Assumptions!$B$66+(Assumptions!$B$67-Assumptions!$B$66)*('Operating Model'!J$77-1)/9 -> 0.014 | K19: =Assumptions!$B$66+(Assumptions!$B$67-Assumptions!$B$66)*('Operating Model'!K$77-1)/9 -> 0.013333333 | ... M19: =Assumptions!$B$66+(Assumptions!$B$67-Assumptions!$B$66)*('Operating Model'!M$77-1)/9 -> 0.012
A20: Less: capex | D20: =-D5*D19 -> -2543.6844 | E20: =-E5*E19 -> -3579.8842 | F20: =-F5*F19 -> -4946.4226 | G20: =-G5*G19 -> -6652.857 | H20: =-H5*H19 -> -8645.1251 | I20: =-I5*I19 -> -10783.993 | J20: =-J5*J19 -> -12840.855 | K20: =-K5*K19 -> -14522.51 | ... M20: =-M5*M19 -> -15633.826
A21: Increase in B2C NOV | D21: =D5-C5 -> 45355.8 | E21: =E5-D5 -> 65215.978 | F21: =F5-E5 -> 90253.58 | G21: =G5-F5 -> 119018.2 | H21: =H5-G5 -> 148008.94 | I21: =I5-H5 -> 171459.77 | J21: =J5-I5 -> 181931.67 | K21: =K5-J5 -> 171984.32 | ... M21: =M5-L5 -> 76850.696
A22: Less: working-capital investment | D22: =-D21*Assumptions!$B$70 -> -453.558 | E22: =-E21*Assumptions!$B$70 -> -652.15978 | F22: =-F21*Assumptions!$B$70 -> -902.5358 | G22: =-G21*Assumptions!$B$70 -> -1190.182 | H22: =-H21*Assumptions!$B$70 -> -1480.0894 | I22: =-I21*Assumptions!$B$70 -> -1714.5977 | J22: =-J21*Assumptions!$B$70 -> -1819.3167 | K22: =-K21*Assumptions!$B$70 -> -1719.8432 | ... M22: =-M21*Assumptions!$B$70 -> -768.50696
A23: Unlevered free cash flow (UFCF) | D23: =D17+D18+D20+D22 -> -1807.3594 | E23: =E17+E18+E20+E22 -> -1278.19 | F23: =F17+F18+F20+F22 -> 190.21045 | G23: =G17+G18+G20+G22 -> 3331.9714 | H23: =H17+H18+H20+H22 -> 9068.5774 | I23: =I17+I18+I20+I22 -> 12627.016 | J23: =J17+J18+J20+J22 -> 16842.186 | K23: =K17+K18+K20+K22 -> 21396.638 | ... M23: =M17+M18+M20+M22 -> 29292.083
A25: Share of year included (FY27E = stub) | D25: =Assumptions!$B$27 -> 0.75068493 | E25: 1 | F25: 1 | G25: 1 | H25: 1 | I25: 1 | J25: 1 | K25: 1 | L25: 1 | M25: 1
A26: Discount period (years, mid-year) | D26: =D25/2 -> 0.37534247 | E26: =Assumptions!$B$27+('Operating Model'!E$77-2)+0.5 -> 1.2506849 | F26: =Assumptions!$B$27+('Operating Model'!F$77-2)+0.5 -> 2.2506849 | G26: =Assumptions!$B$27+('Operating Model'!G$77-2)+0.5 -> 3.2506849 | H26: =Assumptions!$B$27+('Operating Model'!H$77-2)+0.5 -> 4.2506849 | I26: =Assumptions!$B$27+('Operating Model'!I$77-2)+0.5 -> 5.2506849 | J26: =Assumptions!$B$27+('Operating Model'!J$77-2)+0.5 -> 6.2506849 | K26: =Assumptions!$B$27+('Operating Model'!K$77-2)+0.5 -> 7.2506849 | L26: =Assumptions!$B$27+('Operating Model'!L$77-2)+0.5 -> 8.2506849 | M26: =Assumptions!$B$27+('Operating Model'!M$77-2)+0.5 -> 9.2506849
A27: Discount factor | D27: =1/(1+Assumptions!$B$13)^D26 -> 0.95421274 | E27: =1/(1+Assumptions!$B$13)^E26 -> 0.85541226 | F27: =1/(1+Assumptions!$B$13)^F26 -> 0.75499758 | G27: =1/(1+Assumptions!$B$13)^G26 -> 0.66637033 | H27: =1/(1+Assumptions!$B$13)^H26 -> 0.5881468 | I27: =1/(1+Assumptions!$B$13)^I26 -> 0.51910574 | J27: =1/(1+Assumptions!$B$13)^J26 -> 0.45816923 | K27: =1/(1+Assumptions!$B$13)^K26 -> 0.40438591 | ... M27: =1/(1+Assumptions!$B$13)^M26 -> 0.31501859
A28: PV of UFCF | D28: =D23*D25*D27 -> -1294.6353 | E28: =E23*E25*E27 -> -1093.3794 | F28: =F23*F25*F27 -> 143.60843 | G28: =G23*G25*G27 -> 2220.3269 | H28: =H23*H25*H27 -> 5333.6548 | I28: =I23*I25*I27 -> 6554.7565 | J28: =J23*J25*J27 -> 7716.5712 | K28: =K23*K25*K27 -> 8652.4988 | ... M28: =M23*M25*M27 -> 9227.5509
A30: DCF VALUATION SUMMARY
A31: WACC | B31: =Assumptions!B13 -> 0.133
A32: Terminal growth | B32: =Assumptions!B16 -> 0.05
A33: Sum of PV of UFCF (FY27E stub – FY36E) | B33: =SUM(D28:M28) -> 46657.435
A34: Terminal-year UFCF (FY36E) | B34: =M23 -> 29292.083
A35: Terminal value at FY36E (Gordon growth) | B35: =IF(B31>B32,M23*(1+B32)/(B31-B32),NA()) -> 370562.5
A36: PV of terminal value | B36: =B35*M27 -> 116734.08 | C36: TV discounted with the FY36E mid-year factor (consistent with Gordon growth on mid-year flows).
A37: Enterprise value | B37: =B33+B36 -> 163391.51
A38: Add: cash & treasury investments | B38: =Assumptions!B22 -> 18288
A39: Less: financial debt | B39: =-Assumptions!B23 -> 0
A40: Less: contingent GST demands | B40: =-Assumptions!B24 -> -447
A41: Equity value | B41: =SUM(B37:B40) -> 181232.51
A42: Shares outstanding (crore) | B42: =Assumptions!B20 -> 966.75
A43: DCF value per share (₹) | B43: =B41/B42 -> 187.46575
A44: Current share price (₹) | B44: =Assumptions!B19 -> 316.8
A45: Upside / (downside) to current price | B45: =B43/B44-1 -> -0.40825206
A46: Terminal value as % of EV | B46: =B36/B37 -> 0.71444395
A47: Implied terminal EV / FY36E Adj. EBITDA (x) | B47: =B35/M7 -> 5.9046273
A48: Implied EV / FY28E Adj. EBITDA (x) | B48: =B37/E7 -> 34.063273
A49: Implied EV / FY27E B2C NOV (x) | B49: =B37/D5 -> 1.1562155
A50: Terminal-year capex / D&A (x) | B50: =M20/M12 -> 1.0909091 | C50: Above 1.0x is expected while the terminal year still grows ~5–6%.
A53: SENSITIVITY 1 — DCF value per share (₹): WACC (down) vs terminal growth (across). LIVE formulas.
A54: WACC \ Terminal growth | B54: =Assumptions!$B$16+(-0.01) -> 0.04 | C54: =Assumptions!$B$16+(-0.005) -> 0.045 | D54: =Assumptions!$B$16+(0) -> 0.05 | E54: =Assumptions!$B$16+(0.005) -> 0.055 | F54: =Assumptions!$B$16+(0.01) -> 0.06
A55: =Assumptions!$B$13+(-0.02) -> 0.113 | B55: =(SUMPRODUCT($D$23:$M$23,$D$25:$M$25,(1+$A55)^(-$D$26:$M$26))+$M$23*(1+B$54)/($A55-B$54)*(1+$A55)^(-$M$26)+Assumptions!$B$22-Assumptions!$B$23-Assumptions!$B$24)/Assumptions!$B$20 -> 233.64998 | C55: =(SUMPRODUCT($D$23:$M$23,$D$25:$M$25,(1+$A55)^(-$D$26:$M$26))+$M$23*(1+C$54)/($A55-C$54)*(1+$A55)^(-$M$26)+Assumptions!$B$22-Assumptions!$B$23-Assumptions!$B$24)/Assumptions!$B$20 -> 246.26702 | D55: =(SUMPRODUCT($D$23:$M$23,$D$25:$M$25,(1+$A55)^(-$D$26:$M$26))+$M$23*(1+D$54)/($A55-D$54)*(1+$A55)^(-$M$26)+Assumptions!$B$22-Assumptions!$B$23-Assumptions!$B$24)/Assumptions!$B$20 -> 260.88676 | E55: =(SUMPRODUCT($D$23:$M$23,$D$25:$M$25,(1+$A55)^(-$D$26:$M$26))+$M$23*(1+E$54)/($A55-E$54)*(1+$A55)^(-$M$26)+Assumptions!$B$22-Assumptions!$B$23-Assumptions!$B$24)/Assumptions!$B$20 -> 278.02714 | F55: =(SUMPRODUCT($D$23:$M$23,$D$25:$M$25,(1+$A55)^(-$D$26:$M$26))+$M$23*(1+F$54)/($A55-F$54)*(1+$A55)^(-$M$26)+Assumptions!$B$22-Assumptions!$B$23-Assumptions!$B$24)/Assumptions!$B$20 -> 298.40156 | G55: Centre cell equals the DCF value per share in B43 (check below).
A56: =Assumptions!$B$13+(-0.01) -> 0.123 | B56: =(SUMPRODUCT($D$23:$M$23,$D$25:$M$25,(1+$A56)^(-$D$26:$M$26))+$M$23*(1+B$54)/($A56-B$54)*(1+$A56)^(-$M$26)+Assumptions!$B$22-Assumptions!$B$23-Assumptions!$B$24)/Assumptions!$B$20 -> 199.71218 | C56: =(SUMPRODUCT($D$23:$M$23,$D$25:$M$25,(1+$A56)^(-$D$26:$M$26))+$M$23*(1+C$54)/($A56-C$54)*(1+$A56)^(-$M$26)+Assumptions!$B$22-Assumptions!$B$23-Assumptions!$B$24)/Assumptions!$B$20 -> 208.69817 | D56: =(SUMPRODUCT($D$23:$M$23,$D$25:$M$25,(1+$A56)^(-$D$26:$M$26))+$M$23*(1+D$54)/($A56-D$54)*(1+$A56)^(-$M$26)+Assumptions!$B$22-Assumptions!$B$23-Assumptions!$B$24)/Assumptions!$B$20 -> 218.91512 | E56: =(SUMPRODUCT($D$23:$M$23,$D$25:$M$25,(1+$A56)^(-$D$26:$M$26))+$M$23*(1+E$54)/($A56-E$54)*(1+$A56)^(-$M$26)+Assumptions!$B$22-Assumptions!$B$23-Assumptions!$B$24)/Assumptions!$B$20 -> 230.63456 | F56: =(SUMPRODUCT($D$23:$M$23,$D$25:$M$25,(1+$A56)^(-$D$26:$M$26))+$M$23*(1+F$54)/($A56-F$54)*(1+$A56)^(-$M$26)+Assumptions!$B$22-Assumptions!$B$23-Assumptions!$B$24)/Assumptions!$B$20 -> 244.21423
A57: =Assumptions!$B$13+(0) -> 0.133 | B57: =(SUMPRODUCT($D$23:$M$23,$D$25:$M$25,(1+$A57)^(-$D$26:$M$26))+$M$23*(1+B$54)/($A57-B$54)*(1+$A57)^(-$M$26)+Assumptions!$B$22-Assumptions!$B$23-Assumptions!$B$24)/Assumptions!$B$20 -> 173.45565 | C57: =(SUMPRODUCT($D$23:$M$23,$D$25:$M$25,(1+$A57)^(-$D$26:$M$26))+$M$23*(1+C$54)/($A57-C$54)*(1+$A57)^(-$M$26)+Assumptions!$B$22-Assumptions!$B$23-Assumptions!$B$24)/Assumptions!$B$20 -> 180.06269 | D57: =(SUMPRODUCT($D$23:$M$23,$D$25:$M$25,(1+$A57)^(-$D$26:$M$26))+$M$23*(1+D$54)/($A57-D$54)*(1+$A57)^(-$M$26)+Assumptions!$B$22-Assumptions!$B$23-Assumptions!$B$24)/Assumptions!$B$20 -> 187.46575 | E57: =(SUMPRODUCT($D$23:$M$23,$D$25:$M$25,(1+$A57)^(-$D$26:$M$26))+$M$23*(1+E$54)/($A57-E$54)*(1+$A57)^(-$M$26)+Assumptions!$B$22-Assumptions!$B$23-Assumptions!$B$24)/Assumptions!$B$20 -> 195.81792 | F57: =(SUMPRODUCT($D$23:$M$23,$D$25:$M$25,(1+$A57)^(-$D$26:$M$26))+$M$23*(1+F$54)/($A57-F$54)*(1+$A57)^(-$M$26)+Assumptions!$B$22-Assumptions!$B$23-Assumptions!$B$24)/Assumptions!$B$20 -> 205.31423
A58: =Assumptions!$B$13+(0.01) -> 0.143 | B58: =(SUMPRODUCT($D$23:$M$23,$D$25:$M$25,(1+$A58)^(-$D$26:$M$26))+$M$23*(1+B$54)/($A58-B$54)*(1+$A58)^(-$M$26)+Assumptions!$B$22-Assumptions!$B$23-Assumptions!$B$24)/Assumptions!$B$20 -> 152.61989 | C58: =(SUMPRODUCT($D$23:$M$23,$D$25:$M$25,(1+$A58)^(-$D$26:$M$26))+$M$23*(1+C$54)/($A58-C$54)*(1+$A58)^(-$M$26)+Assumptions!$B$22-Assumptions!$B$23-Assumptions!$B$24)/Assumptions!$B$20 -> 157.6021 | D58: =(SUMPRODUCT($D$23:$M$23,$D$25:$M$25,(1+$A58)^(-$D$26:$M$26))+$M$23*(1+D$54)/($A58-D$54)*(1+$A58)^(-$M$26)+Assumptions!$B$22-Assumptions!$B$23-Assumptions!$B$24)/Assumptions!$B$20 -> 163.12003 | E58: =(SUMPRODUCT($D$23:$M$23,$D$25:$M$25,(1+$A58)^(-$D$26:$M$26))+$M$23*(1+E$54)/($A58-E$54)*(1+$A58)^(-$M$26)+Assumptions!$B$22-Assumptions!$B$23-Assumptions!$B$24)/Assumptions!$B$20 -> 169.26499 | F58: =(SUMPRODUCT($D$23:$M$23,$D$25:$M$25,(1+$A58)^(-$D$26:$M$26))+$M$23*(1+F$54)/($A58-F$54)*(1+$A58)^(-$M$26)+Assumptions!$B$22-Assumptions!$B$23-Assumptions!$B$24)/Assumptions!$B$20 -> 176.15031
A59: =Assumptions!$B$13+(0.02) -> 0.153 | B59: =(SUMPRODUCT($D$23:$M$23,$D$25:$M$25,(1+$A59)^(-$D$26:$M$26))+$M$23*(1+B$54)/($A59-B$54)*(1+$A59)^(-$M$26)+Assumptions!$B$22-Assumptions!$B$23-Assumptions!$B$24)/Assumptions!$B$20 -> 135.74625 | C59: =(SUMPRODUCT($D$23:$M$23,$D$25:$M$25,(1+$A59)^(-$D$26:$M$26))+$M$23*(1+C$54)/($A59-C$54)*(1+$A59)^(-$M$26)+Assumptions!$B$22-Assumptions!$B$23-Assumptions!$B$24)/Assumptions!$B$20 -> 139.58129 | D59: =(SUMPRODUCT($D$23:$M$23,$D$25:$M$25,(1+$A59)^(-$D$26:$M$26))+$M$23*(1+D$54)/($A59-D$54)*(1+$A59)^(-$M$26)+Assumptions!$B$22-Assumptions!$B$23-Assumptions!$B$24)/Assumptions!$B$20 -> 143.78867 | E59: =(SUMPRODUCT($D$23:$M$23,$D$25:$M$25,(1+$A59)^(-$D$26:$M$26))+$M$23*(1+E$54)/($A59-E$54)*(1+$A59)^(-$M$26)+Assumptions!$B$22-Assumptions!$B$23-Assumptions!$B$24)/Assumptions!$B$20 -> 148.42536 | F59: =(SUMPRODUCT($D$23:$M$23,$D$25:$M$25,(1+$A59)^(-$D$26:$M$26))+$M$23*(1+F$54)/($A59-F$54)*(1+$A59)^(-$M$26)+Assumptions!$B$22-Assumptions!$B$23-Assumptions!$B$24)/Assumptions!$B$20 -> 153.56063
A60: Check: centre of grid − DCF value per share (should be 0) | B60: =ROUND(D57-B43,6) -> 0
A63: SUM-OF-THE-PARTS (FY28E metrics, valued at Mar-2028, discounted to valuation date) | B63: Metric | C63: FY28E value | D63: Multiple (x) | E63: EV at Mar-28 | F63: PV factor | G63: PV of EV (today) | H63: Per share (₹) | I63: % of EV
A64: Food delivery | B64: EV / Adj. EBITDA | C64: ='Operating Model'!E82 -> 3121.4839 | D64: =Assumptions!$B$73 -> 35 | E64: =C64*D64 -> 109251.94 | F64: =1/(1+Assumptions!$B$13)^((DATE(2028,3,31)-Assumptions!$B$25)/365) -> 0.80336321 | G64: =E64*F64 -> 87768.988 | H64: =G64/Assumptions!$B$20 -> 90.787678 | I64: =G64/$G$69 -> 0.37842692
A65: Blinkit (quick commerce) | B65: EV / NOV | C65: ='Operating Model'!E86 -> 134490.19 | D65: =Assumptions!$B$44*Assumptions!$B$74 -> 1.25 | E65: =C65*D65 -> 168112.74 | F65: =1/(1+Assumptions!$B$13)^((DATE(2028,3,31)-Assumptions!$B$25)/365) -> 0.80336321 | G65: =E65*F65 -> 135055.59 | H65: =G65/Assumptions!$B$20 -> 139.70063 | I65: =G65/$G$69 -> 0.58230899
A66: District (going-out) | B66: EV / NOV | C66: ='Operating Model'!E93 -> 17939.558 | D66: =Assumptions!$B$50*Assumptions!$B$75 -> 0.8 | E66: =C66*D66 -> 14351.646 | F66: =1/(1+Assumptions!$B$13)^((DATE(2028,3,31)-Assumptions!$B$25)/365) -> 0.80336321 | G66: =E66*F66 -> 11529.585 | H66: =G66/Assumptions!$B$20 -> 11.926128 | I66: =G66/$G$69 -> 0.049711241
A67: Hyperpure (B2B) | B67: EV / revenue | C67: ='Operating Model'!E100 -> 5368 | D67: =Assumptions!$B$76 -> 0.4 | E67: =C67*D67 -> 2147.2 | F67: =1/(1+Assumptions!$B$13)^((DATE(2028,3,31)-Assumptions!$B$25)/365) -> 0.80336321 | G67: =E67*F67 -> 1724.9815 | H67: =G67/Assumptions!$B$20 -> 1.7843098 | I67: =G67/$G$69 -> 0.0074374725
A68: Others / corporate drag | B68: EV / Adj. EBITDA (loss) | C68: ='Operating Model'!E116 -> -516.32945 | D68: =Assumptions!$B$77 -> 10 | E68: =C68*D68 -> -5163.2945 | F68: =1/(1+Assumptions!$B$13)^((DATE(2028,3,31)-Assumptions!$B$25)/365) -> 0.80336321 | G68: =E68*F68 -> -4148.0008 | H68: =G68/Assumptions!$B$20 -> -4.2906654 | I68: =G68/$G$69 -> -0.017884622
A69: Consolidated enterprise value | E69: =SUM(E64:E68) -> 288700.23 | G69: =SUM(G64:G68) -> 231931.14 | H69: =SUM(H64:H68) -> 239.90808
A70: Add: cash & treasury investments | G70: =Assumptions!B22 -> 18288
A71: Less: financial debt | G71: =-Assumptions!B23 -> 0
A72: Less: contingent GST demands | G72: =-Assumptions!B24 -> -447
A73: Equity value | G73: =SUM(G69:G72) -> 249772.14
A74: SOTP value per share (₹) | G74: =G73/Assumptions!B20 -> 258.3627
A75: Upside / (downside) to current price | G75: =G74/Assumptions!B19-1 -> -0.18446118
A76: Implied consolidated EV (Mar-28) / FY28E Adj. EBITDA (x) | G76: =E69/'Operating Model'!E110 -> 60.187182
A77: Blended value per share: 50% DCF + 50% SOTP (₹) | G77: =0.5*B43+0.5*G74 -> 222.91422
A78: Market-implied EV today (market cap − cash + debt + contingent) | G78: =Assumptions!B21-Assumptions!B22+Assumptions!B23+Assumptions!B24 -> 288425.4
A81: SCENARIO SUMMARY — STATIC (values pasted from running selector = 1, 2, 3; re-run to refresh)
B82: Bear | C82: Base | D82: Bull
A83: DCF value per share (₹) | B83: 55.981812 | C83: 187.46575 | D83: 368.01241
A84: SOTP value per share (₹) | B84: 173.16064 | C84: 258.3627 | D84: 330.09576
A85: Blended value per share (₹) | B85: 114.57123 | C85: 222.91422 | D85: 349.05409
A86: Blended vs current price | B86: -0.6383484 | C86: -0.29635662 | D86: 0.10181215
A87: FY29E Adj. EBITDA (₹ crore) | B87: 4144.0702 | C87: 9186.6154 | D87: 16068.579
A88: FY29E Adj. EBITDA (US$ mn) | B88: 438.06238 | C88: 971.10099 | D88: 1698.5813
A89: FY28E B2C NOV (US$ bn) | B89: 18.800856 | C89: 21.832112 | D89: 23.967823
A90: FY36E B2C NOV (₹ crore) | B90: 769162.1 | C90: 1302818.9 | D90: 1907572.3
A91: Terminal value % of EV | B91: 0.89023062 | C91: 0.71444395 | D91: 0.69471057
A92: Implied EV / FY28E Adj. EBITDA (x) | B92: 14.393244 | C92: 34.063273 | D92: 44.0058
A95: SENSITIVITY 2 — STATIC: Base-case DCF value per share (₹): Blinkit margin target (down) vs Blinkit FY27E NOV growth (across)
A96: Blinkit margin \ Blinkit FY27E growth | B96: 0.5 | C96: 0.6 | D96: 0.7 | E96: 0.8 | F96: 0.9
A97: 0.03 | B97: 67.44115 | C97: 74.607037 | D97: 84.468215 | E97: 97.806109 | F97: 115.57979
A98: 0.04 | B98: 93.89833 | C98: 111.802 | D98: 136.01262 | E98: 168.30415 | F98: 210.8316
A99: 0.05 | B99: 120.35345 | C99: 148.95163 | D99: 187.46575 | E99: 238.67453 | F99: 305.97756
A100: 0.06 | B100: 146.80856 | C100: 186.10127 | D100: 238.91888 | E100: 309.03878 | F100: 401.08085
A101: 0.07 | B101: 173.26368 | C101: 223.2509 | D101: 290.372 | E101: 379.40304 | F101: 496.18413
A104: SENSITIVITY 3 — STATIC: Base-case DCF value per share (₹): Food-delivery margin target (down) vs District margin target (across)
A105: FD margin \ District margin | B105: 0 | C105: 0.02 | D105: 0.04 | E105: 0.06 | F105: 0.08
A106: 0.05 | B106: 164.95673 | C106: 172.39 | D106: 179.82328 | E106: 187.25655 | F106: 194.68982
A107: 0.055 | B107: 168.77797 | C107: 176.21124 | D107: 183.64451 | E107: 191.07778 | F107: 198.51106
A108: 0.06 | B108: 172.59921 | C108: 180.03248 | D108: 187.46575 | E108: 194.89902 | F108: 202.33229
A109: 0.065 | B109: 176.42044 | C109: 183.85371 | D109: 191.28699 | E109: 198.72026 | F109: 206.15353
A110: 0.07 | B110: 180.24168 | C110: 187.67495 | D110: 195.10822 | E110: 202.54149 | F110: 209.97477
A113: INVESTMENT THESIS
A114: Eternal: From Food-Delivery Platform to Multi-Product Consumer Ecosystem
...

Sheet Mini Projects
A1: ETERNAL LTD. — MINI-PROJECTS
A2: Tags: R = Reported (company disclosure) | C = Calculated from reported figures | D = Derived estimate | A = Assumption (judgement; NOT disclosed) | N/D = not disclosed / not found. Blue = input, black = formula, green = link.
A4: MINI-PROJECT 1 — WHAT IS ONE ZOMATO CUSTOMER WORTH? (food-delivery customer LTV)
A5: Input | B5: Value | C5: Unit | D5: Tag | G5: Source / logic
A6: Food-delivery avg monthly transacting customers, Q4 FY26 | B6: 25.4 | C6: mn | D6: R | G6: Q4 FY26 shareholder letter via HSIE / press.
A7: Food-delivery avg monthly transacting customers, Q1 FY27 | B7: 27.2 | C7: mn | D7: R | G7: Q1 FY27 results (press).
A8: FY25 food-delivery orders | B8: 853 | C8: mn | D8: R | G8: Annual Report FY25 (via MediaNama).
A9: FY25 average monthly transacting customers | B9: 20.6 | C9: mn | D9: R | G9: Annual Report FY25 (via MediaNama).
A10: FY25 orders per customer per month | B10: =B8/(B9*12) -> 3.4506472 | C10: x | D10: C | G10: Orders ÷ (MTU × 12).
A11: Forward orders per customer per month | B11: 3.4 | C11: x | D11: A | G11: Anchored to FY25 calc (3.45). Management: food-delivery frequency stable for several quarters (Q4 FY26 letter, Q7).
A12: FY25 food-delivery NOV | B12: ='Operating Model'!L6 -> 32862 | C12: ₹ cr | D12: C | G12: Operating Model quarterly sum.
A13: FY25 net AOV (NOV ÷ orders) | B13: =B12*10/B8 -> 385.25205 | C13: ₹ | D13: C | G13: NOV × 10 ÷ orders (₹ cr → ₹ mn).
A14: Forward net AOV | B14: 380 | C14: ₹ | D14: A | G14: Management is deliberately lowering AOV (₹99 free-delivery threshold, meals <₹250). Q4 FY26 implied: 9,757 cr ÷ (25.4 mn × 3.4 × 3) ≈ ₹377 (D).
A15: Take rate (adjusted revenue % of NOV), Q4 FY26 | B15: ='Operating Model'!J33 -> 0.32028287 | C15: % | D15: C | G15: Operating Model: adjusted revenue ÷ NOV.
A16: Contribution margin (% of NOV), Q4 FY26 | B16: ='Operating Model'!J45 -> 0.10228554 | C16: % | D16: C | G16: Operating Model: contribution profit ÷ NOV (company-defined contribution).
A17: Adjusted EBITDA margin (% of NOV), Q4 FY26 | B17: ='Operating Model'!J30 -> 0.054524956 | C17: % | D17: C | G17: Fully-loaded view: includes tech, corporate and marketing not allocated to orders.
A18: Annual customer retention (share of customers still ordering next year) | B18: 0.7 | C18: % | D18: A | G18: NOT DISCLOSED. Eternal does not publish cohort retention. TO IMPROVE with cohort data if ever disclosed.
A19: Annual growth in contribution per order | B19: 0.05 | C19: % | D19: A | G19: ASSUMPTION: inflation / take-rate gains.
A20: Discount rate | B20: =Assumptions!B13 -> 0.133 | C20: % | D20: A | G20: Model WACC.
A21: Customer-life horizon cap | B21: 7 | C21: years | D21: A | G21: ASSUMPTION.
A22: Customer acquisition cost (CAC) | B22: 250 | C22: ₹ | D22: A | G22: NOT DISCLOSED. Group advertising & promotion (₹3,350 cr FY26) cannot be split by segment or new vs existing customers. Placeholder; see sensitivity.
A24: Output | B24: Value | C24: Unit | D24: Tag
A25: Orders per customer per year | B25: =B11*12 -> 40.8 | C25: orders | D25: C
A26: Adjusted revenue per order | B26: =B14*B15 -> 121.70749 | C26: ₹ | D26: C | G26: Net AOV × take rate.
A27: Contribution per order | B27: =B14*B16 -> 38.868505 | C27: ₹ | D27: C | G27: Net AOV × contribution margin.
A28: Adj. EBITDA per order (fully loaded) | B28: =B14*B17 -> 20.719483 | C28: ₹ | D28: C
A29: Year-1 contribution per customer | B29: =B25*B27 -> 1585.835 | C29: ₹ | D29: C | G29: Orders/yr × contribution/order.
A30: Year-1 fully-loaded EBITDA per customer | B30: =B25*B28 -> 845.35492 | C30: ₹ | D30: C
A31: Cohort decay factor a = retention × (1+growth) ÷ (1+discount) | B31: =B18*(1+B19)/(1+B20) -> 0.64872021 | C31: x | D31: C
A32: Annuity factor Σ a^(t−1), t = 1..N | B32: =IF(B31=1,B21,(1-B31^B21)/(1-B31)) -> 2.7090923 | C32: x | D32: C | G32: Closed form (1−a^N)/(1−a).
A33: CUSTOMER LTV — contribution basis (before CAC) | B33: =B29/(1+B20)^0.5*B32 -> 4036.1458 | C33: ₹ | D33: C | G33: Year-1 contribution ÷ (1+r)^0.5 × annuity factor (mid-year).
A34: LTV net of CAC — contribution basis | B34: =B33-B22 -> 3786.1458 | C34: ₹ | D34: C
A35: LTV / CAC | B35: =B33/B22 -> 16.144583 | C35: x | D35: C | G35: Rule of thumb >3x healthy.
A36: LTV — fully-loaded Adj. EBITDA basis (before CAC) | B36: =B30/(1+B20)^0.5*B32 -> 2151.5327 | C36: ₹ | D36: C | G36: Conservative floor.
A37: LTV net of CAC — fully-loaded basis | B37: =B36-B22 -> 1901.5327 | C37: ₹ | D37: C
A38: Implied expected customer lifetime | B38: =1/(1-B18) -> 3.3333333 | C38: years | D38: C | G38: 1 ÷ (1 − retention).
A39: Value of current active base (LTV × Q1 FY27 customers) | B39: =B33*B7/10 -> 10978.317 | C39: ₹ cr | D39: C | G39: ₹ × mn ÷ 10.
A40: Food-delivery EV in SOTP (PV today) | B40: =Valuation!G64 -> 87768.988 | C40: ₹ cr | D40: C
A41: SOTP food-delivery EV ÷ value of existing base (x) | B41: =B40/B39 -> 7.9947582 | C41: x | D41: C | G41: Market pays this multiple of the existing base LTV for growth, new cohorts and pricing power.
A43: LTV sensitivity (₹, contribution basis, before CAC): retention (down) vs orders per month (across)
B44: 3 | C44: 3.2 | D44: 3.4 | E44: 3.6 | F44: 3.8
A45: 0.6 | B45: =B$44*12*$B$27/(1+$B$20)^0.5*IF($A45*(1+$B$19)/(1+$B$20)=1,$B$21,(1-($A45*(1+$B$19)/(1+$B$20))^$B$21)/(1-$A45*(1+$B$19)/(1+$B$20))) -> 2912.3951 | C45: =C$44*12*$B$27/(1+$B$20)^0.5*IF($A45*(1+$B$19)/(1+$B$20)=1,$B$21,(1-($A45*(1+$B$19)/(1+$B$20))^$B$21)/(1-$A45*(1+$B$19)/(1+$B$20))) -> 3106.5548 | D45: =D$44*12*$B$27/(1+$B$20)^0.5*IF($A45*(1+$B$19)/(1+$B$20)=1,$B$21,(1-($A45*(1+$B$19)/(1+$B$20))^$B$21)/(1-$A45*(1+$B$19)/(1+$B$20))) -> 3300.7144 | E45: =E$44*12*$B$27/(1+$B$20)^0.5*IF($A45*(1+$B$19)/(1+$B$20)=1,$B$21,(1-($A45*(1+$B$19)/(1+$B$20))^$B$21)/(1-$A45*(1+$B$19)/(1+$B$20))) -> 3494.8741 | F45: =F$44*12*$B$27/(1+$B$20)^0.5*IF($A45*(1+$B$19)/(1+$B$20)=1,$B$21,(1-($A45*(1+$B$19)/(1+$B$20))^$B$21)/(1-$A45*(1+$B$19)/(1+$B$20))) -> 3689.0338
A46: 0.65 | B46: =B$44*12*$B$27/(1+$B$20)^0.5*IF($A46*(1+$B$19)/(1+$B$20)=1,$B$21,(1-($A46*(1+$B$19)/(1+$B$20))^$B$21)/(1-$A46*(1+$B$19)/(1+$B$20))) -> 3210.9797 | C46: =C$44*12*$B$27/(1+$B$20)^0.5*IF($A46*(1+$B$19)/(1+$B$20)=1,$B$21,(1-($A46*(1+$B$19)/(1+$B$20))^$B$21)/(1-$A46*(1+$B$19)/(1+$B$20))) -> 3425.045 | D46: =D$44*12*$B$27/(1+$B$20)^0.5*IF($A46*(1+$B$19)/(1+$B$20)=1,$B$21,(1-($A46*(1+$B$19)/(1+$B$20))^$B$21)/(1-$A46*(1+$B$19)/(1+$B$20))) -> 3639.1104 | E46: =E$44*12*$B$27/(1+$B$20)^0.5*IF($A46*(1+$B$19)/(1+$B$20)=1,$B$21,(1-($A46*(1+$B$19)/(1+$B$20))^$B$21)/(1-$A46*(1+$B$19)/(1+$B$20))) -> 3853.1757 | F46: =F$44*12*$B$27/(1+$B$20)^0.5*IF($A46*(1+$B$19)/(1+$B$20)=1,$B$21,(1-($A46*(1+$B$19)/(1+$B$20))^$B$21)/(1-$A46*(1+$B$19)/(1+$B$20))) -> 4067.241
A47: 0.7 | B47: =B$44*12*$B$27/(1+$B$20)^0.5*IF($A47*(1+$B$19)/(1+$B$20)=1,$B$21,(1-($A47*(1+$B$19)/(1+$B$20))^$B$21)/(1-$A47*(1+$B$19)/(1+$B$20))) -> 3561.3051 | C47: =C$44*12*$B$27/(1+$B$20)^0.5*IF($A47*(1+$B$19)/(1+$B$20)=1,$B$21,(1-($A47*(1+$B$19)/(1+$B$20))^$B$21)/(1-$A47*(1+$B$19)/(1+$B$20))) -> 3798.7255 | D47: =D$44*12*$B$27/(1+$B$20)^0.5*IF($A47*(1+$B$19)/(1+$B$20)=1,$B$21,(1-($A47*(1+$B$19)/(1+$B$20))^$B$21)/(1-$A47*(1+$B$19)/(1+$B$20))) -> 4036.1458 | E47: =E$44*12*$B$27/(1+$B$20)^0.5*IF($A47*(1+$B$19)/(1+$B$20)=1,$B$21,(1-($A47*(1+$B$19)/(1+$B$20))^$B$21)/(1-$A47*(1+$B$19)/(1+$B$20))) -> 4273.5662 | F47: =F$44*12*$B$27/(1+$B$20)^0.5*IF($A47*(1+$B$19)/(1+$B$20)=1,$B$21,(1-($A47*(1+$B$19)/(1+$B$20))^$B$21)/(1-$A47*(1+$B$19)/(1+$B$20))) -> 4510.9865
A48: 0.75 | B48: =B$44*12*$B$27/(1+$B$20)^0.5*IF($A48*(1+$B$19)/(1+$B$20)=1,$B$21,(1-($A48*(1+$B$19)/(1+$B$20))^$B$21)/(1-$A48*(1+$B$19)/(1+$B$20))) -> 3973.0524 | C48: =C$44*12*$B$27/(1+$B$20)^0.5*IF($A48*(1+$B$19)/(1+$B$20)=1,$B$21,(1-($A48*(1+$B$19)/(1+$B$20))^$B$21)/(1-$A48*(1+$B$19)/(1+$B$20))) -> 4237.9225 | D48: =D$44*12*$B$27/(1+$B$20)^0.5*IF($A48*(1+$B$19)/(1+$B$20)=1,$B$21,(1-($A48*(1+$B$19)/(1+$B$20))^$B$21)/(1-$A48*(1+$B$19)/(1+$B$20))) -> 4502.7927 | E48: =E$44*12*$B$27/(1+$B$20)^0.5*IF($A48*(1+$B$19)/(1+$B$20)=1,$B$21,(1-($A48*(1+$B$19)/(1+$B$20))^$B$21)/(1-$A48*(1+$B$19)/(1+$B$20))) -> 4767.6628 | F48: =F$44*12*$B$27/(1+$B$20)^0.5*IF($A48*(1+$B$19)/(1+$B$20)=1,$B$21,(1-($A48*(1+$B$19)/(1+$B$20))^$B$21)/(1-$A48*(1+$B$19)/(1+$B$20))) -> 5032.533
A49: 0.8 | B49: =B$44*12*$B$27/(1+$B$20)^0.5*IF($A49*(1+$B$19)/(1+$B$20)=1,$B$21,(1-($A49*(1+$B$19)/(1+$B$20))^$B$21)/(1-$A49*(1+$B$19)/(1+$B$20))) -> 4457.4393 | C49: =C$44*12*$B$27/(1+$B$20)^0.5*IF($A49*(1+$B$19)/(1+$B$20)=1,$B$21,(1-($A49*(1+$B$19)/(1+$B$20))^$B$21)/(1-$A49*(1+$B$19)/(1+$B$20))) -> 4754.602 | D49: =D$44*12*$B$27/(1+$B$20)^0.5*IF($A49*(1+$B$19)/(1+$B$20)=1,$B$21,(1-($A49*(1+$B$19)/(1+$B$20))^$B$21)/(1-$A49*(1+$B$19)/(1+$B$20))) -> 5051.7646 | E49: =E$44*12*$B$27/(1+$B$20)^0.5*IF($A49*(1+$B$19)/(1+$B$20)=1,$B$21,(1-($A49*(1+$B$19)/(1+$B$20))^$B$21)/(1-$A49*(1+$B$19)/(1+$B$20))) -> 5348.9272 | F49: =F$44*12*$B$27/(1+$B$20)^0.5*IF($A49*(1+$B$19)/(1+$B$20)=1,$B$21,(1-($A49*(1+$B$19)/(1+$B$20))^$B$21)/(1-$A49*(1+$B$19)/(1+$B$20))) -> 5646.0898
A51: LTV / CAC sensitivity: retention (down) vs CAC ₹ (across), at base frequency
B52: 150 | C52: 200 | D52: 250 | E52: 350 | F52: 450
A53: 0.6 | B53: =$B$25*$B$27/(1+$B$20)^0.5*IF($A53*(1+$B$19)/(1+$B$20)=1,$B$21,(1-($A53*(1+$B$19)/(1+$B$20))^$B$21)/(1-$A53*(1+$B$19)/(1+$B$20)))/B$52 -> 22.004763 | C53: =$B$25*$B$27/(1+$B$20)^0.5*IF($A53*(1+$B$19)/(1+$B$20)=1,$B$21,(1-($A53*(1+$B$19)/(1+$B$20))^$B$21)/(1-$A53*(1+$B$19)/(1+$B$20)))/C$52 -> 16.503572 | D53: =$B$25*$B$27/(1+$B$20)^0.5*IF($A53*(1+$B$19)/(1+$B$20)=1,$B$21,(1-($A53*(1+$B$19)/(1+$B$20))^$B$21)/(1-$A53*(1+$B$19)/(1+$B$20)))/D$52 -> 13.202858 | E53: =$B$25*$B$27/(1+$B$20)^0.5*IF($A53*(1+$B$19)/(1+$B$20)=1,$B$21,(1-($A53*(1+$B$19)/(1+$B$20))^$B$21)/(1-$A53*(1+$B$19)/(1+$B$20)))/E$52 -> 9.4306127 | F53: =$B$25*$B$27/(1+$B$20)^0.5*IF($A53*(1+$B$19)/(1+$B$20)=1,$B$21,(1-($A53*(1+$B$19)/(1+$B$20))^$B$21)/(1-$A53*(1+$B$19)/(1+$B$20)))/F$52 -> 7.334921
A54: 0.65 | B54: =$B$25*$B$27/(1+$B$20)^0.5*IF($A54*(1+$B$19)/(1+$B$20)=1,$B$21,(1-($A54*(1+$B$19)/(1+$B$20))^$B$21)/(1-$A54*(1+$B$19)/(1+$B$20)))/B$52 -> 24.260736 | C54: =$B$25*$B$27/(1+$B$20)^0.5*IF($A54*(1+$B$19)/(1+$B$20)=1,$B$21,(1-($A54*(1+$B$19)/(1+$B$20))^$B$21)/(1-$A54*(1+$B$19)/(1+$B$20)))/C$52 -> 18.195552 | D54: =$B$25*$B$27/(1+$B$20)^0.5*IF($A54*(1+$B$19)/(1+$B$20)=1,$B$21,(1-($A54*(1+$B$19)/(1+$B$20))^$B$21)/(1-$A54*(1+$B$19)/(1+$B$20)))/D$52 -> 14.556441 | E54: =$B$25*$B$27/(1+$B$20)^0.5*IF($A54*(1+$B$19)/(1+$B$20)=1,$B$21,(1-($A54*(1+$B$19)/(1+$B$20))^$B$21)/(1-$A54*(1+$B$19)/(1+$B$20)))/E$52 -> 10.397458 | F54: =$B$25*$B$27/(1+$B$20)^0.5*IF($A54*(1+$B$19)/(1+$B$20)=1,$B$21,(1-($A54*(1+$B$19)/(1+$B$20))^$B$21)/(1-$A54*(1+$B$19)/(1+$B$20)))/F$52 -> 8.0869119
A55: 0.7 | B55: =$B$25*$B$27/(1+$B$20)^0.5*IF($A55*(1+$B$19)/(1+$B$20)=1,$B$21,(1-($A55*(1+$B$19)/(1+$B$20))^$B$21)/(1-$A55*(1+$B$19)/(1+$B$20)))/B$52 -> 26.907639 | C55: =$B$25*$B$27/(1+$B$20)^0.5*IF($A55*(1+$B$19)/(1+$B$20)=1,$B$21,(1-($A55*(1+$B$19)/(1+$B$20))^$B$21)/(1-$A55*(1+$B$19)/(1+$B$20)))/C$52 -> 20.180729 | D55: =$B$25*$B$27/(1+$B$20)^0.5*IF($A55*(1+$B$19)/(1+$B$20)=1,$B$21,(1-($A55*(1+$B$19)/(1+$B$20))^$B$21)/(1-$A55*(1+$B$19)/(1+$B$20)))/D$52 -> 16.144583 | E55: =$B$25*$B$27/(1+$B$20)^0.5*IF($A55*(1+$B$19)/(1+$B$20)=1,$B$21,(1-($A55*(1+$B$19)/(1+$B$20))^$B$21)/(1-$A55*(1+$B$19)/(1+$B$20)))/E$52 -> 11.531845 | F55: =$B$25*$B$27/(1+$B$20)^0.5*IF($A55*(1+$B$19)/(1+$B$20)=1,$B$21,(1-($A55*(1+$B$19)/(1+$B$20))^$B$21)/(1-$A55*(1+$B$19)/(1+$B$20)))/F$52 -> 8.969213
A56: 0.75 | B56: =$B$25*$B$27/(1+$B$20)^0.5*IF($A56*(1+$B$19)/(1+$B$20)=1,$B$21,(1-($A56*(1+$B$19)/(1+$B$20))^$B$21)/(1-$A56*(1+$B$19)/(1+$B$20)))/B$52 -> 30.018618 | C56: =$B$25*$B$27/(1+$B$20)^0.5*IF($A56*(1+$B$19)/(1+$B$20)=1,$B$21,(1-($A56*(1+$B$19)/(1+$B$20))^$B$21)/(1-$A56*(1+$B$19)/(1+$B$20)))/C$52 -> 22.513963 | D56: =$B$25*$B$27/(1+$B$20)^0.5*IF($A56*(1+$B$19)/(1+$B$20)=1,$B$21,(1-($A56*(1+$B$19)/(1+$B$20))^$B$21)/(1-$A56*(1+$B$19)/(1+$B$20)))/D$52 -> 18.011171 | E56: =$B$25*$B$27/(1+$B$20)^0.5*IF($A56*(1+$B$19)/(1+$B$20)=1,$B$21,(1-($A56*(1+$B$19)/(1+$B$20))^$B$21)/(1-$A56*(1+$B$19)/(1+$B$20)))/E$52 -> 12.865122 | F56: =$B$25*$B$27/(1+$B$20)^0.5*IF($A56*(1+$B$19)/(1+$B$20)=1,$B$21,(1-($A56*(1+$B$19)/(1+$B$20))^$B$21)/(1-$A56*(1+$B$19)/(1+$B$20)))/F$52 -> 10.006206
A57: 0.8 | B57: =$B$25*$B$27/(1+$B$20)^0.5*IF($A57*(1+$B$19)/(1+$B$20)=1,$B$21,(1-($A57*(1+$B$19)/(1+$B$20))^$B$21)/(1-$A57*(1+$B$19)/(1+$B$20)))/B$52 -> 33.678431 | C57: =$B$25*$B$27/(1+$B$20)^0.5*IF($A57*(1+$B$19)/(1+$B$20)=1,$B$21,(1-($A57*(1+$B$19)/(1+$B$20))^$B$21)/(1-$A57*(1+$B$19)/(1+$B$20)))/C$52 -> 25.258823 | D57: =$B$25*$B$27/(1+$B$20)^0.5*IF($A57*(1+$B$19)/(1+$B$20)=1,$B$21,(1-($A57*(1+$B$19)/(1+$B$20))^$B$21)/(1-$A57*(1+$B$19)/(1+$B$20)))/D$52 -> 20.207058 | E57: =$B$25*$B$27/(1+$B$20)^0.5*IF($A57*(1+$B$19)/(1+$B$20)=1,$B$21,(1-($A57*(1+$B$19)/(1+$B$20))^$B$21)/(1-$A57*(1+$B$19)/(1+$B$20)))/E$52 -> 14.433613 | F57: =$B$25*$B$27/(1+$B$20)^0.5*IF($A57*(1+$B$19)/(1+$B$20)=1,$B$21,(1-($A57*(1+$B$19)/(1+$B$20))^$B$21)/(1-$A57*(1+$B$19)/(1+$B$20)))/F$52 -> 11.226144
A59: Reading the result
A60: One Zomato customer is worth about ₹4,036 on a contribution basis (₹2,152 fully-loaded), against an assumed CAC of ₹250: LTV/CAC ≈ 16.1x. That is attractive but depends on the undisclosed retention and CAC assumptions — see grids.
A61: The existing 27 mn customers are worth ≈ ₹10,978 cr on this basis, while the SOTP gives food delivery ≈ 8x that. The market therefore pays mainly for growth, new cohorts and monetisation upside (including ads), not for today's base.
A62: MINI-PROJECT 2 — CAN ZOMATO BECOME AN ADVERTISING BUSINESS?
A63: DISCLOSURE LIMIT: Eternal does not report advertising revenue separately — ad income sits inside food-delivery revenue ("commission income, ad income and platform fees", AR FY25). Everything below is a SCENARIO model, not a reconstruction of reported ad revenue.
A64: Driver | B64: Low | C64: Base | D64: High | E64: Tag | G64: Source / logic
A65: Restaurant partners on platform (thousand) | B65: 400 | C65: 400 | D65: 400 | E65: R | G65: Q4 FY26 letter: "400k+ restaurants" supported by platforms.
A66: Share of restaurants buying ads in a typical month | B66: 0.1 | C66: 0.2 | D66: 0.35 | E66: A | G66: NOT DISCLOSED.
A67: Average monthly ad spend per advertising restaurant (₹) | B67: 3000 | C67: 6000 | D67: 10000 | E67: A | G67: NOT DISCLOSED. Long-tail restaurants spend little; chains/cloud kitchens much more.
A68: Incremental EBITDA margin on ad revenue | B68: 0.75 | C68: 0.8 | D68: 0.85 | E68: A | G68: ASSUMPTION: ads are sold on existing traffic; main costs are sales force, ad-tech and payment/GST leakage.
A69: Food-delivery NOV FY26 (₹ cr) | B69: ='Operating Model'!M6 -> 37993 | C69: ='Operating Model'!M6 -> 37993 | D69: ='Operating Model'!M6 -> 37993 | E69: C
A70: Food-delivery adjusted revenue FY26 (₹ cr) | B70: ='Operating Model'!M12 -> 11698 | C70: ='Operating Model'!M12 -> 11698 | D70: ='Operating Model'!M12 -> 11698 | E70: C
A71: Food-delivery Adj. EBITDA FY26 (₹ cr) | B71: ='Operating Model'!M20 -> 2017 | C71: ='Operating Model'!M20 -> 2017 | D71: ='Operating Model'!M20 -> 2017 | E71: C
A72: Food-delivery Adj. EBITDA FY28E (₹ cr, active scenario) | B72: ='Operating Model'!E82 -> 3121.4839 | C72: ='Operating Model'!E82 -> 3121.4839 | D72: ='Operating Model'!E82 -> 3121.4839 | E72: C
A73: SOTP food-delivery EV / EBITDA multiple (x) | B73: =Assumptions!$B$73 -> 35 | C73: =Assumptions!$B$73 -> 35 | D73: =Assumptions!$B$73 -> 35 | E73: A
A75: Output
A76: Advertising restaurants (thousand) | B76: =B65*B66 -> 40 | C76: =C65*C66 -> 80 | D76: =D65*D66 -> 140 | E76: C
A77: Annual advertising revenue (₹ cr) | B77: =B65*1000*B66*B67*12/10^7 -> 144 | C77: =C65*1000*C66*C67*12/10^7 -> 576 | D77: =D65*1000*D66*D67*12/10^7 -> 1680 | E77: C
A78: Ad revenue as % of FY26 food-delivery NOV (implied ad take rate) | B78: =B77/B69 -> 0.0037901719 | C78: =C77/C69 -> 0.015160687 | D78: =D77/D69 -> 0.044218672 | E78: C
A79: Ad revenue as % of FY26 food-delivery adjusted revenue | B79: =B77/B70 -> 0.012309797 | C79: =C77/C70 -> 0.049239186 | D79: =D77/D70 -> 0.14361429 | E79: C
A80: Incremental Adj. EBITDA from ads (₹ cr) | B80: =B77*B68 -> 108 | C80: =C77*C68 -> 460.8 | D80: =D77*D68 -> 1428 | E80: C
A81: Ad EBITDA as % of FY26 food-delivery Adj. EBITDA | B81: =B80/B71 -> 0.053544869 | C81: =C80/C71 -> 0.22845811 | D81: =D80/D71 -> 0.70798215 | E81: C
A82: Ad EBITDA as % of FY28E food-delivery Adj. EBITDA | B82: =B80/B72 -> 0.034598929 | C82: =C80/C72 -> 0.1476221 | D82: =D80/D72 -> 0.45747472 | E82: C
A83: Ad EBITDA margin vs food-delivery EBITDA margin on adjusted revenue (FY26) | B83: =B68/(B71/B70) -> 4.3497769 | C83: =C68/(C71/C70) -> 4.639762 | D83: =D68/(D71/D70) -> 4.9297471 | E83: C | G83: >1x means each rupee of ad revenue earns a higher EBITDA margin than the average food-delivery rupee — the "high-margin engine" test.
A84: Valuation impact at food-delivery multiple (₹ cr EV) | B84: =B80*B73 -> 3780 | C84: =C80*C73 -> 16128 | D84: =D80*D73 -> 49980 | E84: C
A85: Valuation impact per share (₹) | B85: =B84/Assumptions!$B$20 -> 3.9100078 | C85: =C84/Assumptions!$B$20 -> 16.6827 | D85: =D84/Assumptions!$B$20 -> 51.698991 | E85: C
A86: Impact as % of SOTP food-delivery EV | B86: =B84/Valuation!$G$64 -> 0.043067604 | C86: =C84/Valuation!$G$64 -> 0.18375511 | D86: =D84/Valuation!$G$64 -> 0.56944943 | E86: C
A87: Is it a meaningful high-margin engine? (test: ≥25% of FD EBITDA = meaningful; 10–25% = material) | B87: =IF(B81>=0.25,"Meaningful",IF(B81>=0.1,"Material","Minor")) -> Minor | C87: =IF(C81>=0.25,"Meaningful",IF(C81>=0.1,"Material","Minor")) -> Material | D87: =IF(D81>=0.25,"Meaningful",IF(D81>=0.1,"Material","Minor")) -> Meaningful | E87: C
A89: Reverse test: what would ads have to be to account for 25% of FY26 food-delivery Adj. EBITDA?
A90: Required ad revenue at base margin (₹ cr) | B90: =0.25*C71/C68 -> 630.3125
A91: Required advertiser penetration at base spend | B91: =B90*10^7/(C65*1000*C67*12) -> 0.21885851
A92: Required ad take rate on FY26 NOV | B92: =B90/C69 -> 0.016590227 | G92: Compare this implied take rate with global food-delivery ad disclosures (DoorDash, Uber Eats, Deliveroo) — TO ADD from their filings; not fetched here.
A94: Ad EBITDA (₹ cr) sensitivity: advertiser penetration (down) vs avg monthly spend ₹ (across), base margin, 400k restaurants
B95: 3000 | C95: 5000 | D95: 7500 | E95: 10000 | F95: 15000
A96: 0.1 | B96: =$C$65*1000*$A96*B$95*12/10^7*$C$68 -> 115.2 | C96: =$C$65*1000*$A96*C$95*12/10^7*$C$68 -> 192 | D96: =$C$65*1000*$A96*D$95*12/10^7*$C$68 -> 288 | E96: =$C$65*1000*$A96*E$95*12/10^7*$C$68 -> 384 | F96: =$C$65*1000*$A96*F$95*12/10^7*$C$68 -> 576
A97: 0.2 | B97: =$C$65*1000*$A97*B$95*12/10^7*$C$68 -> 230.4 | C97: =$C$65*1000*$A97*C$95*12/10^7*$C$68 -> 384 | D97: =$C$65*1000*$A97*D$95*12/10^7*$C$68 -> 576 | E97: =$C$65*1000*$A97*E$95*12/10^7*$C$68 -> 768 | F97: =$C$65*1000*$A97*F$95*12/10^7*$C$68 -> 1152
A98: 0.3 | B98: =$C$65*1000*$A98*B$95*12/10^7*$C$68 -> 345.6 | C98: =$C$65*1000*$A98*C$95*12/10^7*$C$68 -> 576 | D98: =$C$65*1000*$A98*D$95*12/10^7*$C$68 -> 864 | E98: =$C$65*1000*$A98*E$95*12/10^7*$C$68 -> 1152 | F98: =$C$65*1000*$A98*F$95*12/10^7*$C$68 -> 1728
A99: 0.4 | B99: =$C$65*1000*$A99*B$95*12/10^7*$C$68 -> 460.8 | C99: =$C$65*1000*$A99*C$95*12/10^7*$C$68 -> 768 | D99: =$C$65*1000*$A99*D$95*12/10^7*$C$68 -> 1152 | E99: =$C$65*1000*$A99*E$95*12/10^7*$C$68 -> 1536 | F99: =$C$65*1000*$A99*F$95*12/10^7*$C$68 -> 2304
A100: 0.5 | B100: =$C$65*1000*$A100*B$95*12/10^7*$C$68 -> 576 | C100: =$C$65*1000*$A100*C$95*12/10^7*$C$68 -> 960 | D100: =$C$65*1000*$A100*D$95*12/10^7*$C$68 -> 1440 | E100: =$C$65*1000*$A100*E$95*12/10^7*$C$68 -> 1920 | F100: =$C$65*1000*$A100*F$95*12/10^7*$C$68 -> 2880
A102: Reading the result
A103: Base case: ads add ≈ ₹461 cr of EBITDA (23% of FY26 food-delivery EBITDA, ≈ ₹17/share). Range: low ₹108 cr (Minor) to high ₹1,428 cr (Meaningful).
A104: Answer: advertising can be a high-margin add-on (base ad margin ≈ 4.6x the food-delivery EBITDA margin on adjusted revenue) but it only becomes a core engine in the High case. To reach 25% of FD EBITDA needs ≈ 22% advertiser penetration at ₹6,000/month. Ad revenue is not disclosed, so this is a scenario, not a finding.
A105: MINI-PROJECT 3 — WHO CROSS-SELLS BETTER: ZOMATO (ETERNAL) OR SWIGGY?
A106: Period: Q1 FY27 (Apr–Jun 2026). Each company uses its own definitions (Eternal: NOV = after discounts; Swiggy: GOV = before discounts) — compare ratios, not raw levels. Nothing here is fabricated: missing metrics are marked N/D.
A107: Metric | B107: Eternal | C107: Swiggy | D107: Tag | G107: Source / note
A108: Reported operating data
A109: Food-delivery MTU (mn) | B109: 27.2 | C109: 19.2 | D109: R | G109: Eternal Q1 FY27 (press); Swiggy Q1 FY27 shareholder letter.
...

Sheet Sources
A1: ETERNAL LTD. — SOURCES, DATA STATUS AND OPEN ITEMS
A3: # | B3: Item | C3: Used for | D3: Type | E3: Source / URL / caveat
A4: 1 | B4: Eternal Q4 FY26 shareholder letter + audited FY26 results (28-Apr-2026) | C4: FY25/FY26 P&L, segment revenue, segment note, cash flow, balance sheet, GST contingencies, guidance | D4: Primary | E4: https://b.zmtcdn.com/investor-relations/Eternal_Limited_Shareholders_Letter_Q4FY26_Results.pdf (Deloitte unmodified opinion). Tables extracted from PDF text; OCR noise checked by arithmetic tie-out.
A5: 2 | B5: HDFC Securities (HSIE) — Eternal 4QFY26 results review (29-Apr-2026) | C5: Quarterly segment NOV, adjusted revenue, Adj. EBITDA, KPIs (FY24Q4–FY26Q4); SOTP reference multiples | D5: Secondary | E5: https://www.hdfcsec.com/hsl.docs//Eternal%20-%20Q4FY26%20-%20HSIE-202604290654005590303.pdf — INR mn ÷ 10. FY25/FY26 sums tie to company: Adj. EBITDA 1,079 / 1,189; quick-commerce revenue 5,206 / 37,779. TO VERIFY quarter-by-quarter against company letters.
A6: 3 | B6: Eternal Q1 FY27 results (22-Jul-2026), via press | C6: Q1 FY27 NOV, Adj. EBITDA, MTU, orders, stores, cash ₹18,288 cr | D6: Secondary | E6: Business Standard (22/23-Jul-2026); X post @NSuresh_ECW; Inc42; MediaNama earnings-call takeaways; Indian Startup News. Segment sum 606+6+102−65−94 = 555 ties to reported total. TO PULL official Q1 FY27 shareholder letter from eternal.com/investor-relations.
A7: 4 | B7: Eternal Annual Report FY25 (via MediaNama / Storyboard18) | C7: FY25 food-delivery orders (853 mn), AOV, MTU (20.6 mn), Blinkit orders | D7: Secondary | E7: https://www.medianama.com/2025/07/223-eternal-fy25-annual-report-highlights-zomato-blinkit/
A8: 5 | B8: Swiggy Q1 FY27 shareholder letter (Jul-2026) | C8: Swiggy MTU, platform MTU, Instamart orders / AOV / MTU, B2C orders | D8: Primary (snippets) | E8: https://www.swiggy.com/corporate/wp-content/uploads/2026/07/Q1-FY2027-Shareholder-letter.pdf — read via search-result excerpts of the key-metrics tables; column order Q1 FY26 → Q1 FY27. TO VERIFY by opening the PDF.
A9: 6 | B9: Swiggy Q1 FY27 press coverage | C9: Swiggy FD GOV 9,490, adj. EBITDA 292, Instamart GOV 7,907 / NOV 5,817 / EBITDA −778, B2C GOV 18,926 | D9: Secondary | E9: Inc42, BW Marketing World, Business Standard, ViE Stories, YourStory, Medianama (Aug-2026).
A10: 7 | B10: Share price ₹316.80 (17-Sep-2026) | C10: Market cap, upside/downside | D10: Secondary | E10: https://anandrathi.com/stocks/eternal-ltd/share-price-today — REFRESH to latest close.
A11: 8 | B11: India 10-yr G-sec yield ~6.7% (7-Jul-2026) | C11: Risk-free rate | D11: Secondary | E11: https://tradingeconomics.com/india/government-bond-yield/news/564773 — REFRESH.
A12: 9 | B12: ERP 5.5%, beta 1.20, terminal growth 5%, all operating drivers on Assumptions | C12: WACC and forecast | D12: ASSUMPTION | E12: Judgement. Beta and ERP are NOT sourced from a data vendor.
A13: 10 | B13: Mini-project 1 retention, CAC, forward frequency, AOV | C13: Customer LTV | D13: ASSUMPTION | E13: Not disclosed by Eternal. Sensitivity grids show the range.
A14: 11 | B14: Mini-project 2 advertiser penetration, spend, margin | C14: Advertising economics | D14: ASSUMPTION | E14: Ad revenue is not disclosed separately; model is scenario-based.
B16: OPEN ITEMS / KNOWN LIMITATIONS
B17: • Historical sheet FY21 and FY22 line items are still blank (needs the FY22 annual report on BSE, scrip 543320). Left untouched; the model does not depend on them.
B18: • FY25 lease-rental plug (356) differs from FY25 cash lease payments (405) by 49; FY26 ties exactly. Not forced — definitional difference.
B19: • Hyperpure FY26 revenue (5,366) includes non-restaurant sales later moved to Blinkit (1P). FY27E revenue is therefore a reset input, not a growth rate.
B20: • D&A excluding right-of-use assets is a proxy (total D&A − lease principal paid). ROU depreciation is not separately extracted.
B21: • Tax is applied to EBIT from FY27E even though carried-forward losses shelter part of it (management says fully used in FY27) — conservative.
B22: • Share count 966.75 cr includes the ESOP-trust pool; consolidated paid-up capital is 919 cr. Per-share values are ~5% lower than on 919 cr.
B23: • Swiggy "114.5 mn food-delivery orders" in one press summary is actually Instamart orders; rejected and Swiggy food orders derived instead.
B24: • Eternal food-delivery orders / GOV for FY26 and Q1 FY27 not found — Mini-project 1 uses a forward-frequency assumption anchored on FY25 disclosures.
B25: • Static tables (scenario summary, sensitivities 2–3) are pasted values from running the model; they do not update when inputs change. Re-run by switching the selector on Assumptions.
